[[{"dx": -6, "dst_x": 248, "dy": -7, "height": 16, "dst_y": 136, "source": -1, "src_x": 254, "src_y": 143, "width": 16}, {"dx": -6, "dst_x": 264, "dy": -7, "height": 16, "dst_y": 136, "source": -1, "src_x": 270, "src_y": 143, "width": 16}, {"dx": -24, "dst_x": 280, "dy": -19, "height": 8, "dst_y": 132, "source": -1, "src_x": 304, "src_y": 151, "width": 16}, {"dx": -14, "dst_x": 280, "dy": -13, "height": 8, "dst_y": 140, "source": -1, "src_x": 294, "src_y": 153, "width": 16}, {"dx": -24, "dst_x": 296, "dy": -19, "height": 8, "dst_y": 132, "source": -1, "src_x": 320, "src_y": 151, "width": 16}, {"dx": -14, "dst_x": 296, "dy": -14, "height": 8, "dst_y": 140, "source": -1, "src_x": 310, "src_y": 154, "width": 16}, {"dx": -20, "dst_x": 312, "dy": -8, "height": 8, "dst_y": 132, "source": -1, "src_x": 332, "src_y": 140, "width": 16}, {"dx": -16, "dst_x": 312, "dy": -14, "height": 8, "dst_y": 140, "source": -1, "src_x": 328, "src_y": 154, "width": 16}, {"dx": -13, "dst_x": 328, "dy": -7, "height": 8, "dst_y": 132, "source": -1, "src_x": 341, "src_y": 139, "width": 16}, {"dx": -36, "dst_x": 328, "dy": -28, "height": 8, "dst_y": 140, "source": -1, "src_x": 364, "src_y": 168, "width": 16}, {"dx": -18, "dst_x": 344, "dy": -13, "height": 8, "dst_y": 140, "source": -1, "src_x": 362, "src_y": 153, "width": 16}, {"dx": -22, "dst_x": 356, "dy": -9, "height": 8, "dst_y": 132, "source": -1, "src_x": 378, "src_y": 141, "width": 8}, {"dx": -22, "dst_x": 356, "dy": -12, "height": 8, "dst_y": 140, "source": -1, "src_x": 378, "src_y": 152, "width": 8}, {"dx": -15, "dst_x": 276, "dy": -13, "height": 8, "dst_y": 148, "source": -1, "src_x": 291, "src_y": 161, "width": 8}, {"dx": -14, "dst_x": 284, "dy": -13, "height": 8, "dst_y": 148, "source": -1, "src_x": 298, "src_y": 161, "width": 8}, {"dx": -7, "dst_x": 276, "dy": -12, "height": 8, "dst_y": 156, "source": -1, "src_x": 283, "src_y": 168, "width": 8}, {"dx": -13, "dst_x": 284, "dy": -16, "height": 8, "dst_y": 156, "source": -1, "src_x": 297, "src_y": 172, "width": 8}, {"dx": -14, "dst_x": 296, "dy": -16, "height": 16, "dst_y": 152, "source": -1, "src_x": 310, "src_y": 168, "width": 16}, {"dx": -15, "dst_x": 340, "dy": -11, "height": 16, "dst_y": 152, "source": -1, "src_x": 355, "src_y": 163, "width": 8}, {"dx": -18, "dst_x": 348, "dy": -15, "height": 16, "dst_y": 152, "source": -1, "src_x": 366, "src_y": 167, "width": 8}, {"dx": -22, "dst_x": 360, "dy": -5, "height": 16, "dst_y": 152, "source": -1, "src_x": 382, "src_y": 157, "width": 16}, {"dx": -12, "dst_x": 260, "dy": -10, "height": 16, "dst_y": 168, "source": -1, "src_x": 272, "src_y": 178, "width": 8}, {"dx": -13, "dst_x": 268, "dy": -14, "height": 16, "dst_y": 168, "source": -1, "src_x": 281, "src_y": 182, "width": 8}, {"dx": -13, "dst_x": 276, "dy": -15, "height": 16, "dst_y": 168, "source": -1, "src_x": 289, "src_y": 183, "width": 8}, {"dx": -14, "dst_x": 284, "dy": -17, "height": 16, "dst_y": 168, "source": -1, "src_x": 298, "src_y": 185, "width": 8}, {"dx": -14, "dst_x": 296, "dy": -17, "height": 16, "dst_y": 168, "source": -1, "src_x": 310, "src_y": 185, "width": 16}, {"dx": -14, "dst_x": 308, "dy": -17, "height": 8, "dst_y": 164, "source": -1, "src_x": 322, "src_y": 181, "width": 8}, {"dx": -34, "dst_x": 316, "dy": -29, "height": 8, "dst_y": 164, "source": -1, "src_x": 350, "src_y": 193, "width": 8}, {"dx": -34, "dst_x": 308, "dy": -29, "height": 8, "dst_y": 172, "source": -1, "src_x": 342, "src_y": 201, "width": 8}, {"dx": -23, "dst_x": 316, "dy": -17, "height": 8, "dst_y": 172, "source": -1, "src_x": 339, "src_y": 189, "width": 8}, {"dx": -12, "dst_x": 340, "dy": -20, "height": 8, "dst_y": 164, "source": -1, "src_x": 352, "src_y": 184, "width": 8}, {"dx": -17, "dst_x": 348, "dy": -16, "height": 8, "dst_y": 164, "source": -1, "src_x": 365, "src_y": 180, "width": 8}, {"dx": -18, "dst_x": 340, "dy": -16, "height": 8, "dst_y": 172, "source": -1, "src_x": 358, "src_y": 188, "width": 8}, {"dx": -17, "dst_x": 348, "dy": -16, "height": 8, "dst_y": 172, "source": -1, "src_x": 365, "src_y": 188, "width": 8}, {"dx": -12, "dst_x": 276, "dy": -14, "height": 16, "dst_y": 184, "source": -1, "src_x": 288, "src_y": 198, "width": 8}, {"dx": -13, "dst_x": 284, "dy": -18, "height": 16, "dst_y": 184, "source": -1, "src_x": 297, "src_y": 202, "width": 8}, {"dx": -14, "dst_x": 296, "dy": -18, "height": 16, "dst_y": 184, "source": -1, "src_x": 310, "src_y": 202, "width": 16}, {"dx": -17, "dst_x": 344, "dy": -17, "height": 16, "dst_y": 184, "source": -1, "src_x": 361, "src_y": 201, "width": 16}, {"dx": -12, "dst_x": 264, "dy": -12, "height": 8, "dst_y": 196, "source": -1, "src_x": 276, "src_y": 208, "width": 16}, {"dx": -17, "dst_x": 264, "dy": -24, "height": 8, "dst_y": 204, "source": -1, "src_x": 281, "src_y": 228, "width": 16}, {"dx": -13, "dst_x": 276, "dy": -17, "height": 8, "dst_y": 196, "source": -1, "src_x": 289, "src_y": 213, "width": 8}, {"dx": -13, "dst_x": 284, "dy": -18, "height": 8, "dst_y": 196, "source": -1, "src_x": 297, "src_y": 214, "width": 8}, {"dx": -13, "dst_x": 276, "dy": -17, "height": 8, "dst_y": 204, "source": -1, "src_x": 289, "src_y": 221, "width": 8}, {"dx": -13, "dst_x": 284, "dy": -17, "height": 8, "dst_y": 204, "source": -1, "src_x": 297, "src_y": 221, "width": 8}, {"dx": -13, "dst_x": 296, "dy": -18, "height": 8, "dst_y": 196, "source": -1, "src_x": 309, "src_y": 214, "width": 16}, {"dx": -13, "dst_x": 296, "dy": -17, "height": 8, "dst_y": 204, "source": -1, "src_x": 309, "src_y": 221, "width": 16}, {"dx": -13, "dst_x": 312, "dy": -18, "height": 8, "dst_y": 196, "source": -1, "src_x": 325, "src_y": 214, "width": 16}, {"dx": -13, "dst_x": 312, "dy": -17, "height": 8, "dst_y": 204, "source": -1, "src_x": 325, "src_y": 221, "width": 16}, {"dx": 20, "dst_x": 328, "dy": -17, "height": 16, "dst_y": 200, "source": -1, "src_x": 308, "src_y": 217, "width": 16}, {"dx": -22, "dst_x": 356, "dy": -16, "height": 8, "dst_y": 196, "source": -1, "src_x": 378, "src_y": 212, "width": 8}, {"dx": -22, "dst_x": 356, "dy": -17, "height": 8, "dst_y": 204, "source": -1, "src_x": 378, "src_y": 221, "width": 8}]]