[[{"dx": 0, "dst_x": 180, "dy": 1, "height": 8, "dst_y": 92, "source": -1, "src_x": 180, "src_y": 91, "width": 8}, {"dx": 0, "dst_x": 188, "dy": 1, "height": 8, "dst_y": 92, "source": -1, "src_x": 188, "src_y": 91, "width": 8}, {"dx": 0, "dst_x": 196, "dy": 1, "height": 8, "dst_y": 92, "source": -1, "src_x": 196, "src_y": 91, "width": 8}, {"dx": 0, "dst_x": 236, "dy": 1, "height": 8, "dst_y": 92, "source": -1, "src_x": 236, "src_y": 91, "width": 8}, {"dx": -2, "dst_x": 244, "dy": 1, "height": 8, "dst_y": 92, "source": -1, "src_x": 246, "src_y": 91, "width": 8}, {"dx": -3, "dst_x": 188, "dy": -1, "height": 8, "dst_y": 100, "source": -1, "src_x": 191, "src_y": 101, "width": 8}, {"dx": -2, "dst_x": 180, "dy": -1, "height": 8, "dst_y": 108, "source": -1, "src_x": 182, "src_y": 109, "width": 8}, {"dx": -3, "dst_x": 188, "dy": -1, "height": 8, "dst_y": 108, "source": -1, "src_x": 191, "src_y": 109, "width": 8}, {"dx": -3, "dst_x": 200, "dy": 0, "height": 16, "dst_y": 104, "source": -1, "src_x": 203, "src_y": 104, "width": 16}, {"dx": -3, "dst_x": 216, "dy": 0, "height": 16, "dst_y": 104, "source": -1, "src_x": 219, "src_y": 104, "width": 16}, {"dx": -2, "dst_x": 244, "dy": 0, "height": 16, "dst_y": 104, "source": -1, "src_x": 246, "src_y": 104, "width": 8}, {"dx": -3, "dst_x": 180, "dy": -1, "height": 8, "dst_y": 116, "source": -1, "src_x": 183, "src_y": 117, "width": 8}, {"dx": -3, "dst_x": 188, "dy": -1, "height": 8, "dst_y": 116, "source": -1, "src_x": 191, "src_y": 117, "width": 8}, {"dx": -2, "dst_x": 180, "dy": 0, "height": 8, "dst_y": 124, "source": -1, "src_x": 182, "src_y": 124, "width": 8}, {"dx": -3, "dst_x": 188, "dy": -1, "height": 8, "dst_y": 124, "source": -1, "src_x": 191, "src_y": 125, "width": 8}, {"dx": 3, "dst_x": 200, "dy": 1, "height": 16, "dst_y": 120, "source": 1, "src_x": 197, "src_y": 119, "width": 16}, {"dx": -3, "dst_x": 216, "dy": -1, "height": 16, "dst_y": 120, "source": -1, "src_x": 219, "src_y": 121, "width": 16}, {"dx": 3, "dst_x": 216, "dy": 1, "height": 16, "dst_y": 120, "source": 1, "src_x": 213, "src_y": 119, "width": 16}, {"dx": -3, "dst_x": 232, "dy": -1, "height": 16, "dst_y": 120, "source": -1, "src_x": 235, "src_y": 121, "width": 16}, {"dx": 3, "dst_x": 232, "dy": 1, "height": 16, "dst_y": 120, "source": 1, "src_x": 229, "src_y": 119, "width": 16}, {"dx": -2, "dst_x": 244, "dy": 0, "height": 8, "dst_y": 116, "source": -1, "src_x": 246, "src_y": 116, "width": 8}, {"dx": -2, "dst_x": 244, "dy": 0, "height": 8, "dst_y": 124, "source": -1, "src_x": 246, "src_y": 124, "width": 8}, {"dx": -3, "dst_x": 184, "dy": -1, "height": 16, "dst_y": 136, "source": -1, "src_x": 187, "src_y": 137, "width": 16}, {"dx": -3, "dst_x": 200, "dy": -1, "height": 16, "dst_y": 136, "source": -1, "src_x": 203, "src_y": 137, "width": 16}, {"dx": 3, "dst_x": 200, "dy": 1, "height": 16, "dst_y": 136, "source": 1, "src_x": 197, "src_y": 135, "width": 16}, {"dx": -3, "dst_x": 216, "dy": -1, "height": 16, "dst_y": 136, "source": -1, "src_x": 219, "src_y": 137, "width": 16}, {"dx": 3, "dst_x": 216, "dy": 1, "height": 16, "dst_y": 136, "source": 1, "src_x": 213, "src_y": 135, "width": 16}, {"dx": -3, "dst_x": 232, "dy": -1, "height": 16, "dst_y": 136, "source": -1, "src_x": 235, "src_y": 137, "width": 16}, {"dx": 3, "dst_x": 232, "dy": 1, "height": 16, "dst_y": 136, "source": 1, "src_x": 229, "src_y": 135, "width": 16}, {"dx": 4, "dst_x": 172, "dy": 0, "height": 16, "dst_y": 152, "source": 1, "src_x": 168, "src_y": 152, "width": 8}, {"dx": 3, "dst_x": 184, "dy": 0, "height": 16, "dst_y": 152, "source": 1, "src_x": 181, "src_y": 152, "width": 16}, {"dx": 4, "dst_x": 200, "dy": 4, "height": 8, "dst_y": 148, "source": 1, "src_x": 196, "src_y": 144, "width": 16}, {"dx": -3, "dst_x": 216, "dy": -1, "height": 16, "dst_y": 152, "source": -1, "src_x": 219, "src_y": 153, "width": 16}, {"dx": -3, "dst_x": 232, "dy": -1, "height": 16, "dst_y": 152, "source": -1, "src_x": 235, "src_y": 153, "width": 16}], [{"dx": -10, "dst_x": 696, "dy": -4, "height": 16, "dst_y": 312, "source": -1, "src_x": 706, "src_y": 316, "width": 16}, {"dx": 4, "dst_x": 840, "dy": 0, "height": 8, "dst_y": 316, "source": 1, "src_x": 836, "src_y": 316, "width": 16}, {"dx": 9, "dst_x": 856, "dy": 0, "height": 8, "dst_y": 316, "source": 1, "src_x": 847, "src_y": 316, "width": 16}, {"dx": 9, "dst_x": 868, "dy": 3, "height": 8, "dst_y": 316, "source": 1, "src_x": 859, "src_y": 313, "width": 8}, {"dx": 9, "dst_x": 876, "dy": 3, "height": 8, "dst_y": 316, "source": 1, "src_x": 867, "src_y": 313, "width": 8}, {"dx": 9, "dst_x": 888, "dy": 3, "height": 8, "dst_y": 316, "source": 1, "src_x": 879, "src_y": 313, "width": 16}, {"dx": 9, "dst_x": 904, "dy": 3, "height": 8, "dst_y": 316, "source": 1, "src_x": 895, "src_y": 313, "width": 16}, {"dx": 8, "dst_x": 916, "dy": 3, "height": 8, "dst_y": 316, "source": 1, "src_x": 908, "src_y": 313, "width": 8}, {"dx": -13, "dst_x": 952, "dy": -4, "height": 16, "dst_y": 312, "source": -1, "src_x": 965, "src_y": 316, "width": 16}, {"dx": -11, "dst_x": 1032, "dy": -4, "height": 16, "dst_y": 312, "source": -1, "src_x": 1043, "src_y": 316, "width": 16}, {"dx": -10, "dst_x": 692, "dy": 0, "height": 16, "dst_y": 328, "source": -1, "src_x": 702, "src_y": 328, "width": 8}, {"dx": -10, "dst_x": 700, "dy": 0, "height": 16, "dst_y": 328, "source": -1, "src_x": 710, "src_y": 328, "width": 8}, {"dx": -6, "dst_x": 712, "dy": -2, "height": 16, "dst_y": 328, "source": -1, "src_x": 718, "src_y": 330, "width": 16}, {"dx": 0, "dst_x": 820, "dy": 3, "height": 8, "dst_y": 332, "source": 1, "src_x": 820, "src_y": 329, "width": 8}, {"dx": 4, "dst_x": 828, "dy": 3, "height": 8, "dst_y": 332, "source": 1, "src_x": 824, "src_y": 329, "width": 8}, {"dx": 8, "dst_x": 840, "dy": 3, "height": 8, "dst_y": 332, "source": 1, "src_x": 832, "src_y": 329, "width": 16}, {"dx": -9, "dst_x": 856, "dy": -3, "height": 8, "dst_y": 324, "source": -1, "src_x": 865, "src_y": 327, "width": 16}, {"dx": 9, "dst_x": 856, "dy": 3, "height": 8, "dst_y": 332, "source": 1, "src_x": 847, "src_y": 329, "width": 16}, {"dx": -9, "dst_x": 872, "dy": -3, "height": 16, "dst_y": 328, "source": -1, "src_x": 881, "src_y": 331, "width": 16}, {"dx": -9, "dst_x": 884, "dy": -3, "height": 8, "dst_y": 324, "source": -1, "src_x": 893, "src_y": 327, "width": 8}, {"dx": -9, "dst_x": 892, "dy": -3, "height": 8, "dst_y": 324, "source": -1, "src_x": 901, "src_y": 327, "width": 8}, {"dx": -9, "dst_x": 884, "dy": -3, "height": 8, "dst_y": 332, "source": -1, "src_x": 893, "src_y": 335, "width": 8}, {"dx": -9, "dst_x": 892, "dy": -3, "height": 8, "dst_y": 332, "source": -1, "src_x": 901, "src_y": 335, "width": 8}, {"dx": 9, "dst_x": 884, "dy": 3, "height": 8, "dst_y": 332, "source": 1, "src_x": 875, "src_y": 329, "width": 8}, {"dx": 9, "dst_x": 892, "dy": 3, "height": 8, "dst_y": 332, "source": 1, "src_x": 883, "src_y": 329, "width": 8}, {"dx": -9, "dst_x": 904, "dy": -3, "height": 16, "dst_y": 328, "source": -1, "src_x": 913, "src_y": 331, "width": 16}, {"dx": -10, "dst_x": 916, "dy": -5, "height": 8, "dst_y": 324, "source": -1, "src_x": 926, "src_y": 329, "width": 8}, {"dx": -9, "dst_x": 916, "dy": -3, "height": 8, "dst_y": 332, "source": -1, "src_x": 925, "src_y": 335, "width": 8}, {"dx": 0, "dst_x": 924, "dy": -1, "height": 8, "dst_y": 324, "source": 1, "src_x": 924, "src_y": 325, "width": 8}, {"dx": -4, "dst_x": 696, "dy": -2, "height": 16, "dst_y": 344, "source": 1, "src_x": 700, "src_y": 346, "width": 16}, {"dx": -7, "dst_x": 760, "dy": -4, "height": 16, "dst_y": 344, "source": -1, "src_x": 767, "src_y": 348, "width": 16}, {"dx": -7, "dst_x": 776, "dy": -4, "height": 16, "dst_y": 344, "source": -1, "src_x": 783, "src_y": 348, "width": 16}, {"dx": -7, "dst_x": 792, "dy": -4, "height": 16, "dst_y": 344, "source": -1, "src_x": 799, "src_y": 348, "width": 16}, {"dx": -7, "dst_x": 804, "dy": -3, "height": 16, "dst_y": 344, "source": -1, "src_x": 811, "src_y": 347, "width": 8}, {"dx": 8, "dst_x": 812, "dy": 3, "height": 16, "dst_y": 344, "source": 1, "src_x": 804, "src_y": 341, "width": 8}, {"dx": -7, "dst_x": 824, "dy": -3, "height": 16, "dst_y": 344, "source": -1, "src_x": 831, "src_y": 347, "width": 16}, {"dx": 8, "dst_x": 824, "dy": 3, "height": 16, "dst_y": 344, "source": 1, "src_x": 816, "src_y": 341, "width": 16}, {"dx": -8, "dst_x": 840, "dy": -3, "height": 16, "dst_y": 344, "source": -1, "src_x": 848, "src_y": 347, "width": 16}, {"dx": 8, "dst_x": 840, "dy": 3, "height": 16, "dst_y": 344, "source": 1, "src_x": 832, "src_y": 341, "width": 16}, {"dx": -8, "dst_x": 856, "dy": -3, "height": 16, "dst_y": 344, "source": -1, "src_x": 864, "src_y": 347, "width": 16}, {"dx": 8, "dst_x": 856, "dy": 3, "height": 16, "dst_y": 344, "source": 1, "src_x": 848, "src_y": 341, "width": 16}, {"dx": -9, "dst_x": 872, "dy": -3, "height": 16, "dst_y": 344, "source": -1, "src_x": 881, "src_y": 347, "width": 16}, {"dx": 8, "dst_x": 872, "dy": 3, "height": 16, "dst_y": 344, "source": 1, "src_x": 864, "src_y": 341, "width": 16}, {"dx": -9, "dst_x": 888, "dy": -3, "height": 16, "dst_y": 344, "source": -1, "src_x": 897, "src_y": 347, "width": 16}, {"dx": 8, "dst_x": 888, "dy": 3, "height": 16, "dst_y": 344, "source": 1, "src_x": 880, "src_y": 341, "width": 16}, {"dx": -9, "dst_x": 904, "dy": -3, "height": 16, "dst_y": 344, "source": -1, "src_x": 913, "src_y": 347, "width": 16}, {"dx": 8, "dst_x": 904, "dy": 3, "height": 16, "dst_y": 344, "source": 1, "src_x": 896, "src_y": 341, "width": 16}, {"dx": -9, "dst_x": 920, "dy": -3, "height": 16, "dst_y": 344, "source": -1, "src_x": 929, "src_y": 347, "width": 16}, {"dx": -9, "dst_x": 932, "dy": -3, "height": 16, "dst_y": 344, "source": -1, "src_x": 941, "src_y": 347, "width": 8}, {"dx": -10, "dst_x": 696, "dy": -1, "height": 8, "dst_y": 364, "source": -1, "src_x": 706, "src_y": 365, "width": 16}, {"dx": -4, "dst_x": 696, "dy": 0, "height": 8, "dst_y": 356, "source": 1, "src_x": 700, "src_y": 356, "width": 16}, {"dx": 6, "dst_x": 712, "dy": 3, "height": 16, "dst_y": 360, "source": 1, "src_x": 706, "src_y": 357, "width": 16}, {"dx": 7, "dst_x": 728, "dy": 3, "height": 16, "dst_y": 360, "source": 1, "src_x": 721, "src_y": 357, "width": 16}, {"dx": -7, "dst_x": 748, "dy": -4, "height": 16, "dst_y": 360, "source": -1, "src_x": 755, "src_y": 364, "width": 8}, {"dx": 7, "dst_x": 740, "dy": 3, "height": 16, "dst_y": 360, "source": 1, "src_x": 733, "src_y": 357, "width": 8}, {"dx": 7, "dst_x": 748, "dy": 3, "height": 16, "dst_y": 360, "source": 1, "src_x": 741, "src_y": 357, "width": 8}, {"dx": -7, "dst_x": 760, "dy": -4, "height": 16, "dst_y": 360, "source": -1, "src_x": 767, "src_y": 364, "width": 16}, {"dx": 7, "dst_x": 760, "dy": 3, "height": 16, "dst_y": 360, "source": 1, "src_x": 753, "src_y": 357, "width": 16}, {"dx": 7, "dst_x": 776, "dy": 3, "height": 16, "dst_y": 360, "source": 1, "src_x": 769, "src_y": 357, "width": 16}, {"dx": -7, "dst_x": 792, "dy": -3, "height": 16, "dst_y": 360, "source": -1, "src_x": 799, "src_y": 363, "width": 16}, {"dx": 7, "dst_x": 792, "dy": 3, "height": 16, "dst_y": 360, "source": 1, "src_x": 785, "src_y": 357, "width": 16}, {"dx": -7, "dst_x": 808, "dy": -3, "height": 16, "dst_y": 360, "source": -1, "src_x": 815, "src_y": 363, "width": 16}, {"dx": 7, "dst_x": 808, "dy": 3, "height": 16, "dst_y": 360, "source": 1, "src_x": 801, "src_y": 357, "width": 16}, {"dx": -7, "dst_x": 824, "dy": -3, "height": 16, "dst_y": 360, "source": -1, "src_x": 831, "src_y": 363, "width": 16}, {"dx": 8, "dst_x": 824, "dy": 3, "height": 16, "dst_y": 360, "source": 1, "src_x": 816, "src_y": 357, "width": 16}, {"dx": -8, "dst_x": 840, "dy": -3, "height": 16, "dst_y": 360, "source": -1, "src_x": 848, "src_y": 363, "width": 16}, {"dx": 8, "dst_x": 840, "dy": 3, "height": 16, "dst_y": 360, "source": 1, "src_x": 832, "src_y": 357, "width": 16}, {"dx": 8, "dst_x": 856, "dy": 3, "height": 16, "dst_y": 360, "source": 1, "src_x": 848, "src_y": 357, "width": 16}, {"dx": -9, "dst_x": 872, "dy": -3, "height": 16, "dst_y": 360, "source": -1, "src_x": 881, "src_y": 363, "width": 16}, {"dx": -9, "dst_x": 888, "dy": -3, "height": 16, "dst_y": 360, "source": -1, "src_x": 897, "src_y": 363, "width": 16}, {"dx": 8, "dst_x": 888, "dy": 3, "height": 16, "dst_y": 360, "source": 1, "src_x": 880, "src_y": 357, "width": 16}, {"dx": -9, "dst_x": 904, "dy": -3, "height": 16, "dst_y": 360, "source": -1, "src_x": 913, "src_y": 363, "width": 16}, {"dx": 8, "dst_x": 904, "dy": 3, "height": 16, "dst_y": 360, "source": 1, "src_x": 896, "src_y": 357, "width": 16}, {"dx": -9, "dst_x": 920, "dy": -3, "height": 16, "dst_y": 360, "source": -1, "src_x": 929, "src_y": 363, "width": 16}, {"dx": 8, "dst_x": 920, "dy": 3, "height": 16, "dst_y": 360, "source": 1, "src_x": 912, "src_y": 357, "width": 16}, {"dx": -6, "dst_x": 936, "dy": -3, "height": 16, "dst_y": 360, "source": -1, "src_x": 942, "src_y": 363, "width": 16}, {"dx": 6, "dst_x": 952, "dy": 2, "height": 16, "dst_y": 360, "source": 1, "src_x": 946, "src_y": 358, "width": 16}, {"dx": 9, "dst_x": 968, "dy": 3, "height": 8, "dst_y": 364, "source": 1, "src_x": 959, "src_y": 361, "width": 16}, {"dx": -10, "dst_x": 692, "dy": 6, "height": 16, "dst_y": 376, "source": -1, "src_x": 702, "src_y": 370, "width": 8}, {"dx": -6, "dst_x": 700, "dy": -3, "height": 16, "dst_y": 376, "source": -1, "src_x": 706, "src_y": 379, "width": 8}, {"dx": 6, "dst_x": 712, "dy": 3, "height": 16, "dst_y": 376, "source": 1, "src_x": 706, "src_y": 373, "width": 16}, {"dx": 7, "dst_x": 728, "dy": 3, "height": 16, "dst_y": 376, "source": 1, "src_x": 721, "src_y": 373, "width": 16}, {"dx": -7, "dst_x": 744, "dy": -4, "height": 16, "dst_y": 376, "source": -1, "src_x": 751, "src_y": 380, "width": 16}, {"dx": 7, "dst_x": 744, "dy": 3, "height": 16, "dst_y": 376, "source": 1, "src_x": 737, "src_y": 373, "width": 16}, {"dx": 7, "dst_x": 760, "dy": 3, "height": 16, "dst_y": 376, "source": 1, "src_x": 753, "src_y": 373, "width": 16}, {"dx": -7, "dst_x": 776, "dy": -3, "height": 16, "dst_y": 376, "source": -1, "src_x": 783, "src_y": 379, "width": 16}, {"dx": 7, "dst_x": 776, "dy": 3, "height": 16, "dst_y": 376, "source": 1, "src_x": 769, "src_y": 373, "width": 16}, {"dx": -7, "dst_x": 792, "dy": -3, "height": 16, "dst_y": 376, "source": -1, "src_x": 799, "src_y": 379, "width": 16}, {"dx": 7, "dst_x": 792, "dy": 3, "height": 16, "dst_y": 376, "source": 1, "src_x": 785, "src_y": 373, "width": 16}, {"dx": -7, "dst_x": 808, "dy": -3, "height": 16, "dst_y": 376, "source": -1, "src_x": 815, "src_y": 379, "width": 16}, {"dx": 7, "dst_x": 808, "dy": 3, "height": 16, "dst_y": 376, "source": 1, "src_x": 801, "src_y": 373, "width": 16}, {"dx": -7, "dst_x": 824, "dy": -3, "height": 16, "dst_y": 376, "source": -1, "src_x": 831, "src_y": 379, "width": 16}, {"dx": 8, "dst_x": 824, "dy": 3, "height": 16, "dst_y": 376, "source": 1, "src_x": 816, "src_y": 373, "width": 16}, {"dx": -7, "dst_x": 840, "dy": -3, "height": 16, "dst_y": 376, "source": -1, "src_x": 847, "src_y": 379, "width": 16}, {"dx": 8, "dst_x": 840, "dy": 3, "height": 16, "dst_y": 376, "source": 1, "src_x": 832, "src_y": 373, "width": 16}, {"dx": -7, "dst_x": 856, "dy": -3, "height": 16, "dst_y": 376, "source": -1, "src_x": 863, "src_y": 379, "width": 16}, {"dx": 8, "dst_x": 856, "dy": 3, "height": 16, "dst_y": 376, "source": 1, "src_x": 848, "src_y": 373, "width": 16}, {"dx": -9, "dst_x": 872, "dy": -3, "height": 16, "dst_y": 376, "source": -1, "src_x": 881, "src_y": 379, "width": 16}, {"dx": 8, "dst_x": 872, "dy": 3, "height": 16, "dst_y": 376, "source": 1, "src_x": 864, "src_y": 373, "width": 16}, {"dx": -9, "dst_x": 888, "dy": -3, "height": 16, "dst_y": 376, "source": -1, "src_x": 897, "src_y": 379, "width": 16}, {"dx": 8, "dst_x": 888, "dy": 3, "height": 16, "dst_y": 376, "source": 1, "src_x": 880, "src_y": 373, "width": 16}, {"dx": -9, "dst_x": 904, "dy": -3, "height": 16, "dst_y": 376, "source": -1, "src_x": 913, "src_y": 379, "width": 16}, {"dx": -9, "dst_x": 920, "dy": -3, "height": 16, "dst_y": 376, "source": -1, "src_x": 929, "src_y": 379, "width": 16}, {"dx": 8, "dst_x": 920, "dy": 3, "height": 16, "dst_y": 376, "source": 1, "src_x": 912, "src_y": 373, "width": 16}, {"dx": -9, "dst_x": 936, "dy": -4, "height": 16, "dst_y": 376, "source": -1, "src_x": 945, "src_y": 380, "width": 16}, {"dx": 8, "dst_x": 936, "dy": 4, "height": 16, "dst_y": 376, "source": 1, "src_x": 928, "src_y": 372, "width": 16}, {"dx": -9, "dst_x": 952, "dy": -4, "height": 8, "dst_y": 372, "source": -1, "src_x": 961, "src_y": 376, "width": 16}, {"dx": -9, "dst_x": 952, "dy": -4, "height": 8, "dst_y": 380, "source": -1, "src_x": 961, "src_y": 384, "width": 16}, {"dx": 6, "dst_x": 952, "dy": 4, "height": 8, "dst_y": 372, "source": 1, "src_x": 946, "src_y": 368, "width": 16}, {"dx": 8, "dst_x": 952, "dy": 4, "height": 8, "dst_y": 380, "source": 1, "src_x": 944, "src_y": 376, "width": 16}, {"dx": -10, "dst_x": 968, "dy": -4, "height": 8, "dst_y": 380, "source": -1, "src_x": 978, "src_y": 384, "width": 16}, {"dx": 9, "dst_x": 968, "dy": 3, "height": 8, "dst_y": 372, "source": 1, "src_x": 959, "src_y": 369, "width": 16}, {"dx": 10, "dst_x": 984, "dy": 3, "height": 16, "dst_y": 376, "source": 1, "src_x": 974, "src_y": 373, "width": 16}, {"dx": 10, "dst_x": 996, "dy": 3, "height": 8, "dst_y": 372, "source": 1, "src_x": 986, "src_y": 369, "width": 8}, {"dx": 10, "dst_x": 996, "dy": 3, "height": 8, "dst_y": 380, "source": 1, "src_x": 986, "src_y": 377, "width": 8}, {"dx": 10, "dst_x": 1004, "dy": 3, "height": 8, "dst_y": 380, "source": 1, "src_x": 994, "src_y": 377, "width": 8}, {"dx": -10, "dst_x": 696, "dy": 0, "height": 8, "dst_y": 388, "source": -1, "src_x": 706, "src_y": 388, "width": 16}, {"dx": -10, "dst_x": 696, "dy": 0, "height": 8, "dst_y": 396, "source": -1, "src_x": 706, "src_y": 396, "width": 16}, {"dx": 6, "dst_x": 712, "dy": 4, "height": 16, "dst_y": 392, "source": 1, "src_x": 706, "src_y": 388, "width": 16}, {"dx": -7, "dst_x": 728, "dy": -4, "height": 16, "dst_y": 392, "source": -1, "src_x": 735, "src_y": 396, "width": 16}, {"dx": 7, "dst_x": 728, "dy": 3, "height": 16, "dst_y": 392, "source": 1, "src_x": 721, "src_y": 389, "width": 16}, {"dx": -7, "dst_x": 744, "dy": -4, "height": 16, "dst_y": 392, "source": -1, "src_x": 751, "src_y": 396, "width": 16}, {"dx": 7, "dst_x": 744, "dy": 3, "height": 16, "dst_y": 392, "source": 1, "src_x": 737, "src_y": 389, "width": 16}, {"dx": -7, "dst_x": 760, "dy": -3, "height": 16, "dst_y": 392, "source": -1, "src_x": 767, "src_y": 395, "width": 16}, {"dx": 7, "dst_x": 760, "dy": 3, "height": 16, "dst_y": 392, "source": 1, "src_x": 753, "src_y": 389, "width": 16}, {"dx": -7, "dst_x": 776, "dy": -3, "height": 16, "dst_y": 392, "source": -1, "src_x": 783, "src_y": 395, "width": 16}, {"dx": 7, "dst_x": 776, "dy": 3, "height": 16, "dst_y": 392, "source": 1, "src_x": 769, "src_y": 389, "width": 16}, {"dx": -7, "dst_x": 792, "dy": -3, "height": 16, "dst_y": 392, "source": -1, "src_x": 799, "src_y": 395, "width": 16}, {"dx": 7, "dst_x": 792, "dy": 3, "height": 16, "dst_y": 392, "source": 1, "src_x": 785, "src_y": 389, "width": 16}, {"dx": -7, "dst_x": 808, "dy": -3, "height": 16, "dst_y": 392, "source": -1, "src_x": 815, "src_y": 395, "width": 16}, {"dx": -7, "dst_x": 824, "dy": -3, "height": 16, "dst_y": 392, "source": -1, "src_x": 831, "src_y": 395, "width": 16}, {"dx": 8, "dst_x": 824, "dy": 3, "height": 16, "dst_y": 392, "source": 1, "src_x": 816, "src_y": 389, "width": 16}, {"dx": -8, "dst_x": 840, "dy": -3, "height": 16, "dst_y": 392, "source": -1, "src_x": 848, "src_y": 395, "width": 16}, {"dx": -8, "dst_x": 856, "dy": -3, "height": 16, "dst_y": 392, "source": -1, "src_x": 864, "src_y": 395, "width": 16}, {"dx": -9, "dst_x": 872, "dy": -3, "height": 16, "dst_y": 392, "source": -1, "src_x": 881, "src_y": 395, "width": 16}, {"dx": 8, "dst_x": 872, "dy": 3, "height": 16, "dst_y": 392, "source": 1, "src_x": 864, "src_y": 389, "width": 16}, {"dx": -9, "dst_x": 888, "dy": -3, "height": 16, "dst_y": 392, "source": -1, "src_x": 897, "src_y": 395, "width": 16}, {"dx": 8, "dst_x": 888, "dy": 3, "height": 16, "dst_y": 392, "source": 1, "src_x": 880, "src_y": 389, "width": 16}, {"dx": -9, "dst_x": 904, "dy": -3, "height": 16, "dst_y": 392, "source": -1, "src_x": 913, "src_y": 395, "width": 16}, {"dx": 8, "dst_x": 904, "dy": 3, "height": 16, "dst_y": 392, "source": 1, "src_x": 896, "src_y": 389, "width": 16}, {"dx": 10, "dst_x": 920, "dy": 4, "height": 16, "dst_y": 392, "source": 1, "src_x": 910, "src_y": 388, "width": 16}, {"dx": -9, "dst_x": 936, "dy": -4, "height": 16, "dst_y": 392, "source": -1, "src_x": 945, "src_y": 396, "width": 16}, {"dx": 8, "dst_x": 936, "dy": 4, "height": 16, "dst_y": 392, "source": 1, "src_x": 928, "src_y": 388, "width": 16}, {"dx": -9, "dst_x": 952, "dy": -4, "height": 16, "dst_y": 392, "source": -1, "src_x": 961, "src_y": 396, "width": 16}, {"dx": 8, "dst_x": 952, "dy": 4, "height": 16, "dst_y": 392, "source": 1, "src_x": 944, "src_y": 388, "width": 16}, {"dx": -9, "dst_x": 968, "dy": -4, "height": 16, "dst_y": 392, "source": -1, "src_x": 977, "src_y": 396, "width": 16}, {"dx": 8, "dst_x": 968, "dy": 3, "height": 16, "dst_y": 392, "source": 1, "src_x": 960, "src_y": 389, "width": 16}, {"dx": 9, "dst_x": 984, "dy": 3, "height": 16, "dst_y": 392, "source": 1, "src_x": 975, "src_y": 389, "width": 16}, {"dx": 9, "dst_x": 1000, "dy": 3, "height": 16, "dst_y": 392, "source": 1, "src_x": 991, "src_y": 389, "width": 16}, {"dx": -10, "dst_x": 696, "dy": 0, "height": 16, "dst_y": 408, "source": -1, "src_x": 706, "src_y": 408, "width": 16}, {"dx": -6, "dst_x": 712, "dy": -3, "height": 16, "dst_y": 408, "source": -1, "src_x": 718, "src_y": 411, "width": 16}, {"dx": -7, "dst_x": 728, "dy": -4, "height": 16, "dst_y": 408, "source": -1, "src_x": 735, "src_y": 412, "width": 16}, {"dx": 7, "dst_x": 728, "dy": 3, "height": 16, "dst_y": 408, "source": 1, "src_x": 721, "src_y": 405, "width": 16}, {"dx": -7, "dst_x": 744, "dy": -4, "height": 16, "dst_y": 408, "source": -1, "src_x": 751, "src_y": 412, "width": 16}, {"dx": 7, "dst_x": 744, "dy": 3, "height": 16, "dst_y": 408, "source": 1, "src_x": 737, "src_y": 405, "width": 16}, {"dx": -7, "dst_x": 760, "dy": -3, "height": 16, "dst_y": 408, "source": -1, "src_x": 767, "src_y": 411, "width": 16}, {"dx": 7, "dst_x": 760, "dy": 3, "height": 16, "dst_y": 408, "source": 1, "src_x": 753, "src_y": 405, "width": 16}, {"dx": 7, "dst_x": 776, "dy": 3, "height": 16, "dst_y": 408, "source": 1, "src_x": 769, "src_y": 405, "width": 16}, {"dx": -7, "dst_x": 792, "dy": -3, "height": 16, "dst_y": 408, "source": -1, "src_x": 799, "src_y": 411, "width": 16}, {"dx": 7, "dst_x": 792, "dy": 3, "height": 16, "dst_y": 408, "source": 1, "src_x": 785, "src_y": 405, "width": 16}, {"dx": -7, "dst_x": 808, "dy": -3, "height": 16, "dst_y": 408, "source": -1, "src_x": 815, "src_y": 411, "width": 16}, {"dx": 7, "dst_x": 808, "dy": 3, "height": 16, "dst_y": 408, "source": 1, "src_x": 801, "src_y": 405, "width": 16}, {"dx": -7, "dst_x": 824, "dy": -3, "height": 16, "dst_y": 408, "source": -1, "src_x": 831, "src_y": 411, "width": 16}, {"dx": 7, "dst_x": 824, "dy": 3, "height": 16, "dst_y": 408, "source": 1, "src_x": 817, "src_y": 405, "width": 16}, {"dx": -8, "dst_x": 840, "dy": -3, "height": 16, "dst_y": 408, "source": -1, "src_x": 848, "src_y": 411, "width": 16}, {"dx": -8, "dst_x": 856, "dy": -3, "height": 16, "dst_y": 408, "source": -1, "src_x": 864, "src_y": 411, "width": 16}, {"dx": -9, "dst_x": 872, "dy": -3, "height": 16, "dst_y": 408, "source": -1, "src_x": 881, "src_y": 411, "width": 16}, {"dx": 8, "dst_x": 872, "dy": 3, "height": 16, "dst_y": 408, "source": 1, "src_x": 864, "src_y": 405, "width": 16}, {"dx": -9, "dst_x": 888, "dy": -3, "height": 16, "dst_y": 408, "source": -1, "src_x": 897, "src_y": 411, "width": 16}, {"dx": 8, "dst_x": 888, "dy": 3, "height": 16, "dst_y": 408, "source": 1, "src_x": 880, "src_y": 405, "width": 16}, {"dx": -9, "dst_x": 904, "dy": -3, "height": 16, "dst_y": 408, "source": -1, "src_x": 913, "src_y": 411, "width": 16}, {"dx": 8, "dst_x": 904, "dy": 3, "height": 16, "dst_y": 408, "source": 1, "src_x": 896, "src_y": 405, "width": 16}, {"dx": -11, "dst_x": 920, "dy": -3, "height": 16, "dst_y": 408, "source": -1, "src_x": 931, "src_y": 411, "width": 16}, {"dx": -11, "dst_x": 936, "dy": -3, "height": 8, "dst_y": 412, "source": -1, "src_x": 947, "src_y": 415, "width": 16}, {"dx": 9, "dst_x": 936, "dy": 4, "height": 8, "dst_y": 404, "source": 1, "src_x": 927, "src_y": 400, "width": 16}, {"dx": -9, "dst_x": 952, "dy": -4, "height": 16, "dst_y": 408, "source": -1, "src_x": 961, "src_y": 412, "width": 16}, {"dx": 8, "dst_x": 952, "dy": 4, "height": 16, "dst_y": 408, "source": 1, "src_x": 944, "src_y": 404, "width": 16}, {"dx": -9, "dst_x": 968, "dy": -4, "height": 16, "dst_y": 408, "source": -1, "src_x": 977, "src_y": 412, "width": 16}, {"dx": 8, "dst_x": 968, "dy": 3, "height": 16, "dst_y": 408, "source": 1, "src_x": 960, "src_y": 405, "width": 16}, {"dx": -9, "dst_x": 984, "dy": -4, "height": 16, "dst_y": 408, "source": -1, "src_x": 993, "src_y": 412, "width": 16}, {"dx": 9, "dst_x": 984, "dy": 3, "height": 16, "dst_y": 408, "source": 1, "src_x": 975, "src_y": 405, "width": 16}, {"dx": 10, "dst_x": 1000, "dy": 3, "height": 16, "dst_y": 408, "source": 1, "src_x": 990, "src_y": 405, "width": 16}, {"dx": -11, "dst_x": 1032, "dy": 0, "height": 16, "dst_y": 408, "source": -1, "src_x": 1043, "src_y": 408, "width": 16}, {"dx": 3, "dst_x": 1048, "dy": 0, "height": 16, "dst_y": 408, "source": 1, "src_x": 1045, "src_y": 408, "width": 16}, {"dx": -10, "dst_x": 692, "dy": -7, "height": 16, "dst_y": 424, "source": -1, "src_x": 702, "src_y": 431, "width": 8}, {"dx": -6, "dst_x": 700, "dy": -3, "height": 16, "dst_y": 424, "source": -1, "src_x": 706, "src_y": 427, "width": 8}, {"dx": -6, "dst_x": 712, "dy": -4, "height": 8, "dst_y": 420, "source": -1, "src_x": 718, "src_y": 424, "width": 16}, {"dx": -6, "dst_x": 712, "dy": -3, "height": 8, "dst_y": 428, "source": -1, "src_x": 718, "src_y": 431, "width": 16}, {"dx": -7, "dst_x": 728, "dy": -4, "height": 16, "dst_y": 424, "source": -1, "src_x": 735, "src_y": 428, "width": 16}, {"dx": 7, "dst_x": 728, "dy": 3, "height": 16, "dst_y": 424, "source": 1, "src_x": 721, "src_y": 421, "width": 16}, {"dx": -7, "dst_x": 744, "dy": -4, "height": 16, "dst_y": 424, "source": -1, "src_x": 751, "src_y": 428, "width": 16}, {"dx": -7, "dst_x": 760, "dy": -3, "height": 16, "dst_y": 424, "source": -1, "src_x": 767, "src_y": 427, "width": 16}, {"dx": 7, "dst_x": 760, "dy": 3, "height": 16, "dst_y": 424, "source": 1, "src_x": 753, "src_y": 421, "width": 16}, {"dx": 7, "dst_x": 776, "dy": 3, "height": 16, "dst_y": 424, "source": 1, "src_x": 769, "src_y": 421, "width": 16}, {"dx": -7, "dst_x": 792, "dy": -3, "height": 16, "dst_y": 424, "source": -1, "src_x": 799, "src_y": 427, "width": 16}, {"dx": 7, "dst_x": 792, "dy": 3, "height": 16, "dst_y": 424, "source": 1, "src_x": 785, "src_y": 421, "width": 16}, {"dx": -7, "dst_x": 808, "dy": -3, "height": 16, "dst_y": 424, "source": -1, "src_x": 815, "src_y": 427, "width": 16}, {"dx": 7, "dst_x": 808, "dy": 3, "height": 16, "dst_y": 424, "source": 1, "src_x": 801, "src_y": 421, "width": 16}, {"dx": 10, "dst_x": 840, "dy": 5, "height": 16, "dst_y": 424, "source": 1, "src_x": 830, "src_y": 419, "width": 16}, {"dx": -8, "dst_x": 856, "dy": -3, "height": 16, "dst_y": 424, "source": -1, "src_x": 864, "src_y": 427, "width": 16}, {"dx": 8, "dst_x": 856, "dy": 3, "height": 16, "dst_y": 424, "source": 1, "src_x": 848, "src_y": 421, "width": 16}, {"dx": 9, "dst_x": 872, "dy": 4, "height": 16, "dst_y": 424, "source": 1, "src_x": 863, "src_y": 420, "width": 16}, {"dx": -11, "dst_x": 888, "dy": -4, "height": 16, "dst_y": 424, "source": -1, "src_x": 899, "src_y": 428, "width": 16}, {"dx": -9, "dst_x": 900, "dy": -4, "height": 16, "dst_y": 424, "source": -1, "src_x": 909, "src_y": 428, "width": 8}, {"dx": -11, "dst_x": 908, "dy": -3, "height": 16, "dst_y": 424, "source": -1, "src_x": 919, "src_y": 427, "width": 8}, {"dx": -11, "dst_x": 920, "dy": -3, "height": 16, "dst_y": 424, "source": -1, "src_x": 931, "src_y": 427, "width": 16}, {"dx": -11, "dst_x": 936, "dy": -3, "height": 16, "dst_y": 424, "source": -1, "src_x": 947, "src_y": 427, "width": 16}, {"dx": -10, "dst_x": 952, "dy": -3, "height": 16, "dst_y": 424, "source": -1, "src_x": 962, "src_y": 427, "width": 16}, {"dx": 9, "dst_x": 952, "dy": 3, "height": 16, "dst_y": 424, "source": 1, "src_x": 943, "src_y": 421, "width": 16}, {"dx": -9, "dst_x": 968, "dy": -4, "height": 16, "dst_y": 424, "source": -1, "src_x": 977, "src_y": 428, "width": 16}, {"dx": 9, "dst_x": 968, "dy": 3, "height": 16, "dst_y": 424, "source": 1, "src_x": 959, "src_y": 421, "width": 16}, {"dx": -10, "dst_x": 984, "dy": -4, "height": 16, "dst_y": 424, "source": -1, "src_x": 994, "src_y": 428, "width": 16}, {"dx": 10, "dst_x": 984, "dy": 4, "height": 16, "dst_y": 424, "source": 1, "src_x": 974, "src_y": 420, "width": 16}, {"dx": -10, "dst_x": 1000, "dy": -4, "height": 16, "dst_y": 424, "source": -1, "src_x": 1010, "src_y": 428, "width": 16}, {"dx": 10, "dst_x": 1000, "dy": 3, "height": 16, "dst_y": 424, "source": 1, "src_x": 990, "src_y": 421, "width": 16}, {"dx": -9, "dst_x": 1016, "dy": -3, "height": 16, "dst_y": 424, "source": -1, "src_x": 1025, "src_y": 427, "width": 16}, {"dx": -11, "dst_x": 1032, "dy": 0, "height": 16, "dst_y": 424, "source": -1, "src_x": 1043, "src_y": 424, "width": 16}, {"dx": -10, "dst_x": 692, "dy": -1, "height": 16, "dst_y": 440, "source": -1, "src_x": 702, "src_y": 441, "width": 8}, {"dx": -6, "dst_x": 700, "dy": -3, "height": 16, "dst_y": 440, "source": -1, "src_x": 706, "src_y": 443, "width": 8}, {"dx": -6, "dst_x": 712, "dy": -3, "height": 16, "dst_y": 440, "source": -1, "src_x": 718, "src_y": 443, "width": 16}, {"dx": 7, "dst_x": 712, "dy": 3, "height": 16, "dst_y": 440, "source": 1, "src_x": 705, "src_y": 437, "width": 16}, {"dx": -7, "dst_x": 728, "dy": -4, "height": 16, "dst_y": 440, "source": -1, "src_x": 735, "src_y": 444, "width": 16}, {"dx": 7, "dst_x": 728, "dy": 3, "height": 16, "dst_y": 440, "source": 1, "src_x": 721, "src_y": 437, "width": 16}, {"dx": -7, "dst_x": 744, "dy": -4, "height": 16, "dst_y": 440, "source": -1, "src_x": 751, "src_y": 444, "width": 16}, {"dx": 7, "dst_x": 744, "dy": 3, "height": 16, "dst_y": 440, "source": 1, "src_x": 737, "src_y": 437, "width": 16}, {"dx": -7, "dst_x": 760, "dy": -3, "height": 16, "dst_y": 440, "source": -1, "src_x": 767, "src_y": 443, "width": 16}, {"dx": 7, "dst_x": 760, "dy": 3, "height": 16, "dst_y": 440, "source": 1, "src_x": 753, "src_y": 437, "width": 16}, {"dx": -6, "dst_x": 776, "dy": -3, "height": 16, "dst_y": 440, "source": -1, "src_x": 782, "src_y": 443, "width": 16}, {"dx": -7, "dst_x": 792, "dy": -3, "height": 16, "dst_y": 440, "source": -1, "src_x": 799, "src_y": 443, "width": 16}, {"dx": 7, "dst_x": 792, "dy": 3, "height": 16, "dst_y": 440, "source": 1, "src_x": 785, "src_y": 437, "width": 16}, {"dx": -7, "dst_x": 808, "dy": -3, "height": 16, "dst_y": 440, "source": -1, "src_x": 815, "src_y": 443, "width": 16}, {"dx": 7, "dst_x": 808, "dy": 3, "height": 16, "dst_y": 440, "source": 1, "src_x": 801, "src_y": 437, "width": 16}, {"dx": 7, "dst_x": 824, "dy": 3, "height": 16, "dst_y": 440, "source": 1, "src_x": 817, "src_y": 437, "width": 16}, {"dx": 8, "dst_x": 840, "dy": 3, "height": 16, "dst_y": 440, "source": 1, "src_x": 832, "src_y": 437, "width": 16}, {"dx": 10, "dst_x": 856, "dy": 5, "height": 16, "dst_y": 440, "source": 1, "src_x": 846, "src_y": 435, "width": 16}, {"dx": -11, "dst_x": 872, "dy": -4, "height": 16, "dst_y": 440, "source": -1, "src_x": 883, "src_y": 444, "width": 16}, {"dx": -11, "dst_x": 888, "dy": -4, "height": 16, "dst_y": 440, "source": -1, "src_x": 899, "src_y": 444, "width": 16}, {"dx": -11, "dst_x": 904, "dy": -4, "height": 16, "dst_y": 440, "source": -1, "src_x": 915, "src_y": 444, "width": 16}, {"dx": 11, "dst_x": 920, "dy": 4, "height": 16, "dst_y": 440, "source": 1, "src_x": 909, "src_y": 436, "width": 16}, {"dx": -10, "dst_x": 936, "dy": -4, "height": 16, "dst_y": 440, "source": -1, "src_x": 946, "src_y": 444, "width": 16}, {"dx": 10, "dst_x": 936, "dy": 4, "height": 16, "dst_y": 440, "source": 1, "src_x": 926, "src_y": 436, "width": 16}, {"dx": -10, "dst_x": 952, "dy": -4, "height": 16, "dst_y": 440, "source": -1, "src_x": 962, "src_y": 444, "width": 16}, {"dx": 9, "dst_x": 952, "dy": 3, "height": 16, "dst_y": 440, "source": 1, "src_x": 943, "src_y": 437, "width": 16}, {"dx": -10, "dst_x": 968, "dy": -4, "height": 16, "dst_y": 440, "source": -1, "src_x": 978, "src_y": 444, "width": 16}, {"dx": 9, "dst_x": 968, "dy": 3, "height": 16, "dst_y": 440, "source": 1, "src_x": 959, "src_y": 437, "width": 16}, {"dx": -10, "dst_x": 984, "dy": -4, "height": 16, "dst_y": 440, "source": -1, "src_x": 994, "src_y": 444, "width": 16}, {"dx": 10, "dst_x": 984, "dy": 3, "height": 16, "dst_y": 440, "source": 1, "src_x": 974, "src_y": 437, "width": 16}, {"dx": 10, "dst_x": 1000, "dy": 4, "height": 16, "dst_y": 440, "source": 1, "src_x": 990, "src_y": 436, "width": 16}, {"dx": -10, "dst_x": 1016, "dy": -4, "height": 16, "dst_y": 440, "source": -1, "src_x": 1026, "src_y": 444, "width": 16}, {"dx": -11, "dst_x": 1036, "dy": -3, "height": 16, "dst_y": 440, "source": -1, "src_x": 1047, "src_y": 443, "width": 8}, {"dx": -10, "dst_x": 696, "dy": -8, "height": 8, "dst_y": 452, "source": -1, "src_x": 706, "src_y": 460, "width": 16}, {"dx": -10, "dst_x": 696, "dy": -8, "height": 8, "dst_y": 460, "source": -1, "src_x": 706, "src_y": 468, "width": 16}, {"dx": -7, "dst_x": 712, "dy": -4, "height": 16, "dst_y": 456, "source": -1, "src_x": 719, "src_y": 460, "width": 16}, {"dx": 7, "dst_x": 712, "dy": 3, "height": 16, "dst_y": 456, "source": 1, "src_x": 705, "src_y": 453, "width": 16}, {"dx": -7, "dst_x": 728, "dy": -4, "height": 16, "dst_y": 456, "source": -1, "src_x": 735, "src_y": 460, "width": 16}, {"dx": 7, "dst_x": 728, "dy": 3, "height": 16, "dst_y": 456, "source": 1, "src_x": 721, "src_y": 453, "width": 16}, {"dx": -7, "dst_x": 744, "dy": -4, "height": 16, "dst_y": 456, "source": -1, "src_x": 751, "src_y": 460, "width": 16}, {"dx": 7, "dst_x": 744, "dy": 3, "height": 16, "dst_y": 456, "source": 1, "src_x": 737, "src_y": 453, "width": 16}, {"dx": -7, "dst_x": 760, "dy": -4, "height": 16, "dst_y": 456, "source": -1, "src_x": 767, "src_y": 460, "width": 16}, {"dx": 7, "dst_x": 776, "dy": 4, "height": 16, "dst_y": 456, "source": 1, "src_x": 769, "src_y": 452, "width": 16}, {"dx": -7, "dst_x": 792, "dy": -3, "height": 16, "dst_y": 456, "source": -1, "src_x": 799, "src_y": 459, "width": 16}, {"dx": 7, "dst_x": 792, "dy": 3, "height": 16, "dst_y": 456, "source": 1, "src_x": 785, "src_y": 453, "width": 16}, {"dx": -7, "dst_x": 808, "dy": -3, "height": 16, "dst_y": 456, "source": -1, "src_x": 815, "src_y": 459, "width": 16}, {"dx": 7, "dst_x": 808, "dy": 3, "height": 16, "dst_y": 456, "source": 1, "src_x": 801, "src_y": 453, "width": 16}, {"dx": 7, "dst_x": 824, "dy": 3, "height": 16, "dst_y": 456, "source": 1, "src_x": 817, "src_y": 453, "width": 16}, {"dx": 8, "dst_x": 840, "dy": 3, "height": 16, "dst_y": 456, "source": 1, "src_x": 832, "src_y": 453, "width": 16}, {"dx": 8, "dst_x": 856, "dy": 3, "height": 16, "dst_y": 456, "source": 1, "src_x": 848, "src_y": 453, "width": 16}, {"dx": -11, "dst_x": 872, "dy": -4, "height": 16, "dst_y": 456, "source": -1, "src_x": 883, "src_y": 460, "width": 16}, {"dx": -11, "dst_x": 888, "dy": -4, "height": 16, "dst_y": 456, "source": -1, "src_x": 899, "src_y": 460, "width": 16}, {"dx": -11, "dst_x": 904, "dy": -4, "height": 16, "dst_y": 456, "source": -1, "src_x": 915, "src_y": 460, "width": 16}, {"dx": 11, "dst_x": 904, "dy": 4, "height": 16, "dst_y": 456, "source": 1, "src_x": 893, "src_y": 452, "width": 16}, {"dx": -11, "dst_x": 920, "dy": -4, "height": 16, "dst_y": 456, "source": -1, "src_x": 931, "src_y": 460, "width": 16}, {"dx": -11, "dst_x": 936, "dy": -4, "height": 16, "dst_y": 456, "source": -1, "src_x": 947, "src_y": 460, "width": 16}, {"dx": 11, "dst_x": 952, "dy": 4, "height": 16, "dst_y": 456, "source": 1, "src_x": 941, "src_y": 452, "width": 16}, {"dx": 11, "dst_x": 968, "dy": 4, "height": 16, "dst_y": 456, "source": 1, "src_x": 957, "src_y": 452, "width": 16}, {"dx": 10, "dst_x": 984, "dy": 4, "height": 16, "dst_y": 456, "source": 1, "src_x": 974, "src_y": 452, "width": 16}, {"dx": -10, "dst_x": 1000, "dy": -4, "height": 16, "dst_y": 456, "source": -1, "src_x": 1010, "src_y": 460, "width": 16}, {"dx": 10, "dst_x": 1000, "dy": 4, "height": 16, "dst_y": 456, "source": 1, "src_x": 990, "src_y": 452, "width": 16}, {"dx": -10, "dst_x": 1016, "dy": -4, "height": 16, "dst_y": 456, "source": -1, "src_x": 1026, "src_y": 460, "width": 16}, {"dx": -11, "dst_x": 1036, "dy": -3, "height": 16, "dst_y": 456, "source": -1, "src_x": 1047, "src_y": 459, "width": 8}, {"dx": -10, "dst_x": 696, "dy": -10, "height": 16, "dst_y": 472, "source": -1, "src_x": 706, "src_y": 482, "width": 16}, {"dx": -7, "dst_x": 712, "dy": -4, "height": 16, "dst_y": 472, "source": -1, "src_x": 719, "src_y": 476, "width": 16}, {"dx": 7, "dst_x": 712, "dy": 3, "height": 16, "dst_y": 472, "source": 1, "src_x": 705, "src_y": 469, "width": 16}, {"dx": -7, "dst_x": 728, "dy": -4, "height": 16, "dst_y": 472, "source": -1, "src_x": 735, "src_y": 476, "width": 16}, {"dx": 7, "dst_x": 728, "dy": 3, "height": 16, "dst_y": 472, "source": 1, "src_x": 721, "src_y": 469, "width": 16}, {"dx": 7, "dst_x": 744, "dy": 5, "height": 16, "dst_y": 472, "source": 1, "src_x": 737, "src_y": 467, "width": 16}, {"dx": -7, "dst_x": 760, "dy": -4, "height": 16, "dst_y": 472, "source": -1, "src_x": 767, "src_y": 476, "width": 16}, {"dx": 7, "dst_x": 760, "dy": 4, "height": 16, "dst_y": 472, "source": 1, "src_x": 753, "src_y": 468, "width": 16}, {"dx": -7, "dst_x": 776, "dy": -3, "height": 16, "dst_y": 472, "source": -1, "src_x": 783, "src_y": 475, "width": 16}, {"dx": 7, "dst_x": 776, "dy": 4, "height": 16, "dst_y": 472, "source": 1, "src_x": 769, "src_y": 468, "width": 16}, {"dx": -7, "dst_x": 792, "dy": -3, "height": 16, "dst_y": 472, "source": -1, "src_x": 799, "src_y": 475, "width": 16}, {"dx": 7, "dst_x": 792, "dy": 3, "height": 16, "dst_y": 472, "source": 1, "src_x": 785, "src_y": 469, "width": 16}, {"dx": -7, "dst_x": 808, "dy": -3, "height": 16, "dst_y": 472, "source": -1, "src_x": 815, "src_y": 475, "width": 16}, {"dx": 7, "dst_x": 808, "dy": 3, "height": 16, "dst_y": 472, "source": 1, "src_x": 801, "src_y": 469, "width": 16}, {"dx": 7, "dst_x": 824, "dy": 3, "height": 16, "dst_y": 472, "source": 1, "src_x": 817, "src_y": 469, "width": 16}, {"dx": 10, "dst_x": 856, "dy": 5, "height": 16, "dst_y": 472, "source": 1, "src_x": 846, "src_y": 467, "width": 16}, {"dx": -11, "dst_x": 872, "dy": -4, "height": 16, "dst_y": 472, "source": -1, "src_x": 883, "src_y": 476, "width": 16}, {"dx": 10, "dst_x": 872, "dy": 5, "height": 16, "dst_y": 472, "source": 1, "src_x": 862, "src_y": 467, "width": 16}, {"dx": -11, "dst_x": 888, "dy": -4, "height": 16, "dst_y": 472, "source": -1, "src_x": 899, "src_y": 476, "width": 16}, {"dx": 10, "dst_x": 888, "dy": 4, "height": 16, "dst_y": 472, "source": 1, "src_x": 878, "src_y": 468, "width": 16}, {"dx": -11, "dst_x": 904, "dy": -4, "height": 16, "dst_y": 472, "source": -1, "src_x": 915, "src_y": 476, "width": 16}, {"dx": 10, "dst_x": 904, "dy": 4, "height": 16, "dst_y": 472, "source": 1, "src_x": 894, "src_y": 468, "width": 16}, {"dx": -11, "dst_x": 920, "dy": -4, "height": 16, "dst_y": 472, "source": -1, "src_x": 931, "src_y": 476, "width": 16}, {"dx": 10, "dst_x": 920, "dy": 4, "height": 16, "dst_y": 472, "source": 1, "src_x": 910, "src_y": 468, "width": 16}, {"dx": -11, "dst_x": 936, "dy": -4, "height": 16, "dst_y": 472, "source": -1, "src_x": 947, "src_y": 476, "width": 16}, {"dx": -11, "dst_x": 952, "dy": -4, "height": 16, "dst_y": 472, "source": -1, "src_x": 963, "src_y": 476, "width": 16}, {"dx": 11, "dst_x": 952, "dy": 4, "height": 16, "dst_y": 472, "source": 1, "src_x": 941, "src_y": 468, "width": 16}, {"dx": -11, "dst_x": 968, "dy": -4, "height": 16, "dst_y": 472, "source": -1, "src_x": 979, "src_y": 476, "width": 16}, {"dx": 11, "dst_x": 968, "dy": 4, "height": 16, "dst_y": 472, "source": 1, "src_x": 957, "src_y": 468, "width": 16}, {"dx": 10, "dst_x": 984, "dy": 4, "height": 16, "dst_y": 472, "source": 1, "src_x": 974, "src_y": 468, "width": 16}, {"dx": -10, "dst_x": 1000, "dy": -4, "height": 16, "dst_y": 472, "source": -1, "src_x": 1010, "src_y": 476, "width": 16}, {"dx": 10, "dst_x": 1000, "dy": 4, "height": 16, "dst_y": 472, "source": 1, "src_x": 990, "src_y": 468, "width": 16}, {"dx": -10, "dst_x": 1016, "dy": -4, "height": 16, "dst_y": 472, "source": -1, "src_x": 1026, "src_y": 476, "width": 16}, {"dx": -11, "dst_x": 1032, "dy": -4, "height": 16, "dst_y": 472, "source": -1, "src_x": 1043, "src_y": 476, "width": 16}, {"dx": -10, "dst_x": 696, "dy": -11, "height": 16, "dst_y": 488, "source": -1, "src_x": 706, "src_y": 499, "width": 16}, {"dx": -7, "dst_x": 712, "dy": -4, "height": 16, "dst_y": 488, "source": -1, "src_x": 719, "src_y": 492, "width": 16}, {"dx": 7, "dst_x": 712, "dy": 3, "height": 16, "dst_y": 488, "source": 1, "src_x": 705, "src_y": 485, "width": 16}, {"dx": -7, "dst_x": 728, "dy": -4, "height": 16, "dst_y": 488, "source": -1, "src_x": 735, "src_y": 492, "width": 16}, {"dx": 7, "dst_x": 728, "dy": 3, "height": 16, "dst_y": 488, "source": 1, "src_x": 721, "src_y": 485, "width": 16}, {"dx": -7, "dst_x": 744, "dy": -4, "height": 16, "dst_y": 488, "source": -1, "src_x": 751, "src_y": 492, "width": 16}, {"dx": 7, "dst_x": 744, "dy": 4, "height": 16, "dst_y": 488, "source": 1, "src_x": 737, "src_y": 484, "width": 16}, {"dx": -7, "dst_x": 760, "dy": -4, "height": 16, "dst_y": 488, "source": -1, "src_x": 767, "src_y": 492, "width": 16}, {"dx": 7, "dst_x": 760, "dy": 4, "height": 16, "dst_y": 488, "source": 1, "src_x": 753, "src_y": 484, "width": 16}, {"dx": -7, "dst_x": 776, "dy": -3, "height": 16, "dst_y": 488, "source": -1, "src_x": 783, "src_y": 491, "width": 16}, {"dx": 7, "dst_x": 776, "dy": 4, "height": 16, "dst_y": 488, "source": 1, "src_x": 769, "src_y": 484, "width": 16}, {"dx": -7, "dst_x": 792, "dy": -3, "height": 16, "dst_y": 488, "source": -1, "src_x": 799, "src_y": 491, "width": 16}, {"dx": 7, "dst_x": 792, "dy": 3, "height": 16, "dst_y": 488, "source": 1, "src_x": 785, "src_y": 485, "width": 16}, {"dx": -7, "dst_x": 808, "dy": -3, "height": 16, "dst_y": 488, "source": -1, "src_x": 815, "src_y": 491, "width": 16}, {"dx": 7, "dst_x": 808, "dy": 3, "height": 16, "dst_y": 488, "source": 1, "src_x": 801, "src_y": 485, "width": 16}, {"dx": 7, "dst_x": 824, "dy": 3, "height": 16, "dst_y": 488, "source": 1, "src_x": 817, "src_y": 485, "width": 16}, {"dx": 7, "dst_x": 840, "dy": 3, "height": 16, "dst_y": 488, "source": 1, "src_x": 833, "src_y": 485, "width": 16}, {"dx": -10, "dst_x": 856, "dy": -5, "height": 16, "dst_y": 488, "source": -1, "src_x": 866, "src_y": 493, "width": 16}, {"dx": -11, "dst_x": 872, "dy": -4, "height": 16, "dst_y": 488, "source": -1, "src_x": 883, "src_y": 492, "width": 16}, {"dx": 10, "dst_x": 872, "dy": 4, "height": 16, "dst_y": 488, "source": 1, "src_x": 862, "src_y": 484, "width": 16}, {"dx": -11, "dst_x": 888, "dy": -4, "height": 16, "dst_y": 488, "source": -1, "src_x": 899, "src_y": 492, "width": 16}, {"dx": 10, "dst_x": 888, "dy": 4, "height": 16, "dst_y": 488, "source": 1, "src_x": 878, "src_y": 484, "width": 16}, {"dx": -11, "dst_x": 904, "dy": -4, "height": 16, "dst_y": 488, "source": -1, "src_x": 915, "src_y": 492, "width": 16}, {"dx": 10, "dst_x": 904, "dy": 4, "height": 16, "dst_y": 488, "source": 1, "src_x": 894, "src_y": 484, "width": 16}, {"dx": -11, "dst_x": 920, "dy": -4, "height": 16, "dst_y": 488, "source": -1, "src_x": 931, "src_y": 492, "width": 16}, {"dx": 10, "dst_x": 920, "dy": 4, "height": 16, "dst_y": 488, "source": 1, "src_x": 910, "src_y": 484, "width": 16}, {"dx": -11, "dst_x": 936, "dy": -4, "height": 16, "dst_y": 488, "source": -1, "src_x": 947, "src_y": 492, "width": 16}, {"dx": 10, "dst_x": 936, "dy": 4, "height": 16, "dst_y": 488, "source": 1, "src_x": 926, "src_y": 484, "width": 16}, {"dx": 11, "dst_x": 952, "dy": 4, "height": 16, "dst_y": 488, "source": 1, "src_x": 941, "src_y": 484, "width": 16}, {"dx": -11, "dst_x": 968, "dy": -4, "height": 16, "dst_y": 488, "source": -1, "src_x": 979, "src_y": 492, "width": 16}, {"dx": 11, "dst_x": 968, "dy": 4, "height": 16, "dst_y": 488, "source": 1, "src_x": 957, "src_y": 484, "width": 16}, {"dx": -9, "dst_x": 984, "dy": -5, "height": 16, "dst_y": 488, "source": -1, "src_x": 993, "src_y": 493, "width": 16}, {"dx": -10, "dst_x": 1000, "dy": -4, "height": 16, "dst_y": 488, "source": -1, "src_x": 1010, "src_y": 492, "width": 16}, {"dx": 10, "dst_x": 1000, "dy": 4, "height": 16, "dst_y": 488, "source": 1, "src_x": 990, "src_y": 484, "width": 16}, {"dx": -10, "dst_x": 1016, "dy": -4, "height": 16, "dst_y": 488, "source": -1, "src_x": 1026, "src_y": 492, "width": 16}, {"dx": -11, "dst_x": 1032, "dy": -4, "height": 16, "dst_y": 488, "source": -1, "src_x": 1043, "src_y": 492, "width": 16}, {"dx": -7, "dst_x": 712, "dy": -4, "height": 16, "dst_y": 504, "source": -1, "src_x": 719, "src_y": 508, "width": 16}, {"dx": 7, "dst_x": 712, "dy": 3, "height": 16, "dst_y": 504, "source": 1, "src_x": 705, "src_y": 501, "width": 16}, {"dx": -7, "dst_x": 728, "dy": -4, "height": 16, "dst_y": 504, "source": -1, "src_x": 735, "src_y": 508, "width": 16}, {"dx": 7, "dst_x": 728, "dy": 3, "height": 16, "dst_y": 504, "source": 1, "src_x": 721, "src_y": 501, "width": 16}, {"dx": -7, "dst_x": 744, "dy": -4, "height": 16, "dst_y": 504, "source": -1, "src_x": 751, "src_y": 508, "width": 16}, {"dx": 7, "dst_x": 744, "dy": 4, "height": 16, "dst_y": 504, "source": 1, "src_x": 737, "src_y": 500, "width": 16}, {"dx": -7, "dst_x": 776, "dy": -3, "height": 16, "dst_y": 504, "source": -1, "src_x": 783, "src_y": 507, "width": 16}, {"dx": 7, "dst_x": 776, "dy": 3, "height": 16, "dst_y": 504, "source": 1, "src_x": 769, "src_y": 501, "width": 16}, {"dx": -7, "dst_x": 792, "dy": -3, "height": 16, "dst_y": 504, "source": -1, "src_x": 799, "src_y": 507, "width": 16}, {"dx": 7, "dst_x": 792, "dy": 3, "height": 16, "dst_y": 504, "source": 1, "src_x": 785, "src_y": 501, "width": 16}, {"dx": -7, "dst_x": 808, "dy": -3, "height": 16, "dst_y": 504, "source": -1, "src_x": 815, "src_y": 507, "width": 16}, {"dx": 7, "dst_x": 808, "dy": 3, "height": 16, "dst_y": 504, "source": 1, "src_x": 801, "src_y": 501, "width": 16}, {"dx": 7, "dst_x": 840, "dy": 3, "height": 16, "dst_y": 504, "source": 1, "src_x": 833, "src_y": 501, "width": 16}, {"dx": -10, "dst_x": 856, "dy": -4, "height": 16, "dst_y": 504, "source": -1, "src_x": 866, "src_y": 508, "width": 16}, {"dx": -11, "dst_x": 872, "dy": -4, "height": 16, "dst_y": 504, "source": -1, "src_x": 883, "src_y": 508, "width": 16}, {"dx": 10, "dst_x": 872, "dy": 4, "height": 16, "dst_y": 504, "source": 1, "src_x": 862, "src_y": 500, "width": 16}, {"dx": 10, "dst_x": 888, "dy": 3, "height": 16, "dst_y": 504, "source": 1, "src_x": 878, "src_y": 501, "width": 16}, {"dx": -12, "dst_x": 904, "dy": -5, "height": 16, "dst_y": 504, "source": -1, "src_x": 916, "src_y": 509, "width": 16}, {"dx": -11, "dst_x": 920, "dy": -5, "height": 16, "dst_y": 504, "source": -1, "src_x": 931, "src_y": 509, "width": 16}, {"dx": -11, "dst_x": 936, "dy": -5, "height": 16, "dst_y": 504, "source": -1, "src_x": 947, "src_y": 509, "width": 16}, {"dx": -11, "dst_x": 952, "dy": -4, "height": 16, "dst_y": 504, "source": -1, "src_x": 963, "src_y": 508, "width": 16}, {"dx": 11, "dst_x": 952, "dy": 4, "height": 16, "dst_y": 504, "source": 1, "src_x": 941, "src_y": 500, "width": 16}, {"dx": 11, "dst_x": 968, "dy": 4, "height": 16, "dst_y": 504, "source": 1, "src_x": 957, "src_y": 500, "width": 16}, {"dx": -9, "dst_x": 984, "dy": -4, "height": 16, "dst_y": 504, "source": -1, "src_x": 993, "src_y": 508, "width": 16}, {"dx": 10, "dst_x": 984, "dy": 4, "height": 16, "dst_y": 504, "source": 1, "src_x": 974, "src_y": 500, "width": 16}, {"dx": -10, "dst_x": 1000, "dy": -4, "height": 16, "dst_y": 504, "source": -1, "src_x": 1010, "src_y": 508, "width": 16}, {"dx": 10, "dst_x": 1000, "dy": 4, "height": 16, "dst_y": 504, "source": 1, "src_x": 990, "src_y": 500, "width": 16}, {"dx": -10, "dst_x": 1012, "dy": -4, "height": 16, "dst_y": 504, "source": -1, "src_x": 1022, "src_y": 508, "width": 8}, {"dx": -11, "dst_x": 1032, "dy": -4, "height": 16, "dst_y": 504, "source": -1, "src_x": 1043, "src_y": 508, "width": 16}, {"dx": -7, "dst_x": 700, "dy": -4, "height": 16, "dst_y": 520, "source": -1, "src_x": 707, "src_y": 524, "width": 8}, {"dx": 0, "dst_x": 712, "dy": -1, "height": 16, "dst_y": 520, "source": 1, "src_x": 712, "src_y": 521, "width": 16}, {"dx": 3, "dst_x": 728, "dy": 4, "height": 16, "dst_y": 520, "source": 1, "src_x": 725, "src_y": 516, "width": 16}, {"dx": 3, "dst_x": 744, "dy": 4, "height": 16, "dst_y": 520, "source": 1, "src_x": 741, "src_y": 516, "width": 16}, {"dx": 3, "dst_x": 760, "dy": 3, "height": 16, "dst_y": 520, "source": 1, "src_x": 757, "src_y": 517, "width": 16}, {"dx": -7, "dst_x": 776, "dy": -3, "height": 16, "dst_y": 520, "source": -1, "src_x": 783, "src_y": 523, "width": 16}, {"dx": 7, "dst_x": 776, "dy": 3, "height": 16, "dst_y": 520, "source": 1, "src_x": 769, "src_y": 517, "width": 16}, {"dx": -7, "dst_x": 792, "dy": -3, "height": 16, "dst_y": 520, "source": -1, "src_x": 799, "src_y": 523, "width": 16}, {"dx": 7, "dst_x": 792, "dy": 3, "height": 16, "dst_y": 520, "source": 1, "src_x": 785, "src_y": 517, "width": 16}, {"dx": -7, "dst_x": 808, "dy": -3, "height": 16, "dst_y": 520, "source": -1, "src_x": 815, "src_y": 523, "width": 16}, {"dx": 7, "dst_x": 808, "dy": 3, "height": 16, "dst_y": 520, "source": 1, "src_x": 801, "src_y": 517, "width": 16}, {"dx": 7, "dst_x": 824, "dy": 3, "height": 16, "dst_y": 520, "source": 1, "src_x": 817, "src_y": 517, "width": 16}, {"dx": 7, "dst_x": 840, "dy": 3, "height": 16, "dst_y": 520, "source": 1, "src_x": 833, "src_y": 517, "width": 16}, {"dx": -10, "dst_x": 856, "dy": -5, "height": 16, "dst_y": 520, "source": -1, "src_x": 866, "src_y": 525, "width": 16}, {"dx": 31, "dst_x": 872, "dy": 17, "height": 16, "dst_y": 520, "source": 1, "src_x": 841, "src_y": 503, "width": 16}, {"dx": -12, "dst_x": 888, "dy": -2, "height": 8, "dst_y": 516, "source": -1, "src_x": 900, "src_y": 518, "width": 16}, {"dx": 31, "dst_x": 888, "dy": 16, "height": 8, "dst_y": 524, "source": 1, "src_x": 857, "src_y": 508, "width": 16}, {"dx": -12, "dst_x": 904, "dy": -5, "height": 16, "dst_y": 520, "source": -1, "src_x": 916, "src_y": 525, "width": 16}, {"dx": -11, "dst_x": 920, "dy": -5, "height": 16, "dst_y": 520, "source": -1, "src_x": 931, "src_y": 525, "width": 16}, {"dx": -11, "dst_x": 936, "dy": -5, "height": 16, "dst_y": 520, "source": -1, "src_x": 947, "src_y": 525, "width": 16}, {"dx": -11, "dst_x": 952, "dy": -4, "height": 16, "dst_y": 520, "source": -1, "src_x": 963, "src_y": 524, "width": 16}, {"dx": -9, "dst_x": 968, "dy": -4, "height": 16, "dst_y": 520, "source": -1, "src_x": 977, "src_y": 524, "width": 16}, {"dx": 10, "dst_x": 968, "dy": 4, "height": 16, "dst_y": 520, "source": 1, "src_x": 958, "src_y": 516, "width": 16}, {"dx": -9, "dst_x": 984, "dy": -4, "height": 16, "dst_y": 520, "source": -1, "src_x": 993, "src_y": 524, "width": 16}, {"dx": 10, "dst_x": 984, "dy": 4, "height": 16, "dst_y": 520, "source": 1, "src_x": 974, "src_y": 516, "width": 16}, {"dx": 10, "dst_x": 1000, "dy": 4, "height": 16, "dst_y": 520, "source": 1, "src_x": 990, "src_y": 516, "width": 16}, {"dx": -3, "dst_x": 1016, "dy": -1, "height": 16, "dst_y": 520, "source": 1, "src_x": 1019, "src_y": 521, "width": 16}, {"dx": -11, "dst_x": 1032, "dy": -4, "height": 16, "dst_y": 520, "source": -1, "src_x": 1043, "src_y": 524, "width": 16}, {"dx": -10, "dst_x": 696, "dy": -8, "height": 16, "dst_y": 536, "source": -1, "src_x": 706, "src_y": 544, "width": 16}, {"dx": -7, "dst_x": 728, "dy": -7, "height": 16, "dst_y": 536, "source": -1, "src_x": 735, "src_y": 543, "width": 16}, {"dx": 2, "dst_x": 744, "dy": 2, "height": 16, "dst_y": 536, "source": -1, "src_x": 742, "src_y": 534, "width": 16}, {"dx": 0, "dst_x": 760, "dy": -1, "height": 16, "dst_y": 536, "source": -1, "src_x": 760, "src_y": 537, "width": 16}, {"dx": -4, "dst_x": 776, "dy": -3, "height": 16, "dst_y": 536, "source": -1, "src_x": 780, "src_y": 539, "width": 16}, {"dx": -3, "dst_x": 792, "dy": -3, "height": 16, "dst_y": 536, "source": -1, "src_x": 795, "src_y": 539, "width": 16}, {"dx": -1, "dst_x": 808, "dy": -2, "height": 16, "dst_y": 536, "source": -1, "src_x": 809, "src_y": 538, "width": 16}, {"dx": -10, "dst_x": 856, "dy": -5, "height": 8, "dst_y": 532, "source": -1, "src_x": 866, "src_y": 537, "width": 16}, {"dx": -11, "dst_x": 872, "dy": -5, "height": 16, "dst_y": 536, "source": -1, "src_x": 883, "src_y": 541, "width": 16}, {"dx": -11, "dst_x": 888, "dy": -5, "height": 16, "dst_y": 536, "source": -1, "src_x": 899, "src_y": 541, "width": 16}, {"dx": -11, "dst_x": 904, "dy": -5, "height": 16, "dst_y": 536, "source": -1, "src_x": 915, "src_y": 541, "width": 16}, {"dx": -11, "dst_x": 920, "dy": -5, "height": 16, "dst_y": 536, "source": -1, "src_x": 931, "src_y": 541, "width": 16}, {"dx": -11, "dst_x": 936, "dy": -5, "height": 16, "dst_y": 536, "source": -1, "src_x": 947, "src_y": 541, "width": 16}, {"dx": -11, "dst_x": 952, "dy": -4, "height": 16, "dst_y": 536, "source": -1, "src_x": 963, "src_y": 540, "width": 16}, {"dx": -9, "dst_x": 964, "dy": -4, "height": 8, "dst_y": 532, "source": -1, "src_x": 973, "src_y": 536, "width": 8}, {"dx": -9, "dst_x": 972, "dy": -4, "height": 8, "dst_y": 532, "source": -1, "src_x": 981, "src_y": 536, "width": 8}, {"dx": -9, "dst_x": 964, "dy": -4, "height": 8, "dst_y": 540, "source": -1, "src_x": 973, "src_y": 544, "width": 8}, {"dx": -9, "dst_x": 972, "dy": -4, "height": 8, "dst_y": 540, "source": -1, "src_x": 981, "src_y": 544, "width": 8}, {"dx": 10, "dst_x": 964, "dy": 4, "height": 8, "dst_y": 540, "source": 1, "src_x": 954, "src_y": 536, "width": 8}, {"dx": 10, "dst_x": 972, "dy": 4, "height": 8, "dst_y": 540, "source": 1, "src_x": 962, "src_y": 536, "width": 8}, {"dx": -9, "dst_x": 984, "dy": -4, "height": 16, "dst_y": 536, "source": -1, "src_x": 993, "src_y": 540, "width": 16}, {"dx": -9, "dst_x": 1000, "dy": -4, "height": 16, "dst_y": 536, "source": -1, "src_x": 1009, "src_y": 540, "width": 16}, {"dx": -9, "dst_x": 1012, "dy": -4, "height": 8, "dst_y": 532, "source": -1, "src_x": 1021, "src_y": 536, "width": 8}, {"dx": -9, "dst_x": 1012, "dy": -4, "height": 8, "dst_y": 540, "source": -1, "src_x": 1021, "src_y": 544, "width": 8}, {"dx": -3, "dst_x": 1012, "dy": -1, "height": 8, "dst_y": 532, "source": 1, "src_x": 1015, "src_y": 533, "width": 8}, {"dx": -11, "dst_x": 1032, "dy": -2, "height": 16, "dst_y": 536, "source": -1, "src_x": 1043, "src_y": 538, "width": 16}, {"dx": -10, "dst_x": 696, "dy": -6, "height": 8, "dst_y": 548, "source": -1, "src_x": 706, "src_y": 554, "width": 16}, {"dx": -3, "dst_x": 724, "dy": -6, "height": 16, "dst_y": 552, "source": -1, "src_x": 727, "src_y": 558, "width": 8}, {"dx": 3, "dst_x": 732, "dy": -6, "height": 16, "dst_y": 552, "source": -1, "src_x": 729, "src_y": 558, "width": 8}, {"dx": -6, "dst_x": 744, "dy": -6, "height": 16, "dst_y": 552, "source": -1, "src_x": 750, "src_y": 558, "width": 16}, {"dx": -4, "dst_x": 760, "dy": -6, "height": 16, "dst_y": 552, "source": -1, "src_x": 764, "src_y": 558, "width": 16}, {"dx": -16, "dst_x": 788, "dy": -6, "height": 8, "dst_y": 548, "source": -1, "src_x": 804, "src_y": 554, "width": 8}, {"dx": -8, "dst_x": 796, "dy": -6, "height": 8, "dst_y": 548, "source": -1, "src_x": 804, "src_y": 554, "width": 8}, {"dx": -8, "dst_x": 796, "dy": -6, "height": 8, "dst_y": 556, "source": -1, "src_x": 804, "src_y": 562, "width": 8}, {"dx": -5, "dst_x": 808, "dy": -6, "height": 16, "dst_y": 552, "source": -1, "src_x": 813, "src_y": 558, "width": 16}, {"dx": 0, "dst_x": 824, "dy": -6, "height": 16, "dst_y": 552, "source": -1, "src_x": 824, "src_y": 558, "width": 16}, {"dx": -7, "dst_x": 856, "dy": -6, "height": 8, "dst_y": 548, "source": -1, "src_x": 863, "src_y": 554, "width": 16}, {"dx": -7, "dst_x": 856, "dy": -6, "height": 8, "dst_y": 556, "source": -1, "src_x": 863, "src_y": 562, "width": 16}, {"dx": -9, "dst_x": 888, "dy": -6, "height": 16, "dst_y": 552, "source": -1, "src_x": 897, "src_y": 558, "width": 16}, {"dx": -9, "dst_x": 952, "dy": -6, "height": 16, "dst_y": 552, "source": -1, "src_x": 961, "src_y": 558, "width": 16}, {"dx": -11, "dst_x": 1000, "dy": -6, "height": 16, "dst_y": 552, "source": -1, "src_x": 1011, "src_y": 558, "width": 16}, {"dx": -11, "dst_x": 1016, "dy": -6, "height": 16, "dst_y": 552, "source": -1, "src_x": 1027, "src_y": 558, "width": 16}, {"dx": -11, "dst_x": 1032, "dy": -6, "height": 8, "dst_y": 548, "source": -1, "src_x": 1043, "src_y": 554, "width": 16}]]