[[{"dx": -14, "dst_x": 884, "dy": -4, "height": 8, "dst_y": 324, "source": 1, "src_x": 898, "src_y": 328, "width": 8}, {"dx": -14, "dst_x": 884, "dy": -3, "height": 8, "dst_y": 332, "source": 1, "src_x": 898, "src_y": 335, "width": 8}, {"dx": 2, "dst_x": 892, "dy": -2, "height": 8, "dst_y": 332, "source": 1, "src_x": 890, "src_y": 334, "width": 8}, {"dx": -16, "dst_x": 904, "dy": -3, "height": 8, "dst_y": 332, "source": 1, "src_x": 920, "src_y": 335, "width": 16}, {"dx": -11, "dst_x": 916, "dy": -3, "height": 8, "dst_y": 332, "source": 1, "src_x": 927, "src_y": 335, "width": 8}, {"dx": -11, "dst_x": 924, "dy": -3, "height": 8, "dst_y": 332, "source": 1, "src_x": 935, "src_y": 335, "width": 8}, {"dx": -11, "dst_x": 936, "dy": -3, "height": 8, "dst_y": 332, "source": 1, "src_x": 947, "src_y": 335, "width": 16}, {"dx": 29, "dst_x": 952, "dy": 8, "height": 8, "dst_y": 332, "source": -1, "src_x": 923, "src_y": 324, "width": 16}, {"dx": -11, "dst_x": 952, "dy": -3, "height": 8, "dst_y": 332, "source": 1, "src_x": 963, "src_y": 335, "width": 16}, {"dx": 29, "dst_x": 964, "dy": 8, "height": 8, "dst_y": 332, "source": -1, "src_x": 935, "src_y": 324, "width": 8}, {"dx": -14, "dst_x": 884, "dy": -4, "height": 8, "dst_y": 340, "source": 1, "src_x": 898, "src_y": 344, "width": 8}, {"dx": -14, "dst_x": 884, "dy": -5, "height": 8, "dst_y": 348, "source": 1, "src_x": 898, "src_y": 353, "width": 8}, {"dx": -14, "dst_x": 888, "dy": -5, "height": 16, "dst_y": 360, "source": 1, "src_x": 902, "src_y": 365, "width": 16}, {"dx": 33, "dst_x": 988, "dy": 10, "height": 16, "dst_y": 360, "source": -1, "src_x": 955, "src_y": 350, "width": 8}, {"dx": -14, "dst_x": 888, "dy": -5, "height": 16, "dst_y": 376, "source": 1, "src_x": 902, "src_y": 381, "width": 16}, {"dx": 33, "dst_x": 988, "dy": 12, "height": 16, "dst_y": 376, "source": -1, "src_x": 955, "src_y": 364, "width": 8}, {"dx": 33, "dst_x": 988, "dy": 12, "height": 8, "dst_y": 388, "source": -1, "src_x": 955, "src_y": 376, "width": 8}], [{"dx": -1, "dst_x": 628, "dy": 1, "height": 8, "dst_y": 236, "source": 1, "src_x": 629, "src_y": 235, "width": 8}, {"dx": 0, "dst_x": 636, "dy": 1, "height": 8, "dst_y": 236, "source": 1, "src_x": 636, "src_y": 235, "width": 8}, {"dx": 0, "dst_x": 648, "dy": 1, "height": 8, "dst_y": 236, "source": 1, "src_x": 648, "src_y": 235, "width": 16}, {"dx": 0, "dst_x": 664, "dy": 1, "height": 8, "dst_y": 236, "source": 1, "src_x": 664, "src_y": 235, "width": 16}, {"dx": -3, "dst_x": 616, "dy": -1, "height": 16, "dst_y": 248, "source": 1, "src_x": 619, "src_y": 249, "width": 16}, {"dx": -1, "dst_x": 628, "dy": 0, "height": 16, "dst_y": 248, "source": 1, "src_x": 629, "src_y": 248, "width": 8}, {"dx": 12, "dst_x": 628, "dy": 6, "height": 16, "dst_y": 264, "source": -1, "src_x": 616, "src_y": 258, "width": 8}, {"dx": 15, "dst_x": 676, "dy": 7, "height": 16, "dst_y": 264, "source": -1, "src_x": 661, "src_y": 257, "width": 8}, {"dx": -3, "dst_x": 616, "dy": 0, "height": 16, "dst_y": 280, "source": 1, "src_x": 619, "src_y": 280, "width": 16}, {"dx": 12, "dst_x": 628, "dy": 6, "height": 8, "dst_y": 276, "source": -1, "src_x": 616, "src_y": 270, "width": 8}, {"dx": 12, "dst_x": 636, "dy": 6, "height": 8, "dst_y": 276, "source": -1, "src_x": 624, "src_y": 270, "width": 8}, {"dx": 12, "dst_x": 628, "dy": 7, "height": 8, "dst_y": 284, "source": -1, "src_x": 616, "src_y": 277, "width": 8}, {"dx": 12, "dst_x": 636, "dy": 6, "height": 8, "dst_y": 284, "source": -1, "src_x": 624, "src_y": 278, "width": 8}, {"dx": 28, "dst_x": 680, "dy": 14, "height": 16, "dst_y": 280, "source": -1, "src_x": 652, "src_y": 266, "width": 16}, {"dx": 12, "dst_x": 632, "dy": 7, "height": 8, "dst_y": 292, "source": -1, "src_x": 620, "src_y": 285, "width": 16}, {"dx": 12, "dst_x": 648, "dy": 7, "height": 8, "dst_y": 292, "source": -1, "src_x": 636, "src_y": 285, "width": 16}, {"dx": 10, "dst_x": 648, "dy": 6, "height": 8, "dst_y": 300, "source": -1, "src_x": 638, "src_y": 294, "width": 16}, {"dx": 16, "dst_x": 676, "dy": 6, "height": 16, "dst_y": 296, "source": -1, "src_x": 660, "src_y": 290, "width": 8}]]