[[{"dx": 0, "dst_x": 392, "dy": -3, "height": 8, "dst_y": 156, "source": -1, "src_x": 392, "src_y": 159, "width": 16}, {"dx": -7, "dst_x": 408, "dy": -3, "height": 8, "dst_y": 156, "source": -1, "src_x": 415, "src_y": 159, "width": 16}, {"dx": 0, "dst_x": 456, "dy": -3, "height": 8, "dst_y": 156, "source": -1, "src_x": 456, "src_y": 159, "width": 16}, {"dx": -8, "dst_x": 472, "dy": -3, "height": 8, "dst_y": 156, "source": -1, "src_x": 480, "src_y": 159, "width": 16}, {"dx": -16, "dst_x": 488, "dy": -3, "height": 8, "dst_y": 156, "source": -1, "src_x": 504, "src_y": 159, "width": 16}, {"dx": 0, "dst_x": 504, "dy": -3, "height": 8, "dst_y": 156, "source": -1, "src_x": 504, "src_y": 159, "width": 16}, {"dx": 0, "dst_x": 516, "dy": -3, "height": 8, "dst_y": 156, "source": -1, "src_x": 516, "src_y": 159, "width": 8}, {"dx": -10, "dst_x": 524, "dy": -3, "height": 8, "dst_y": 156, "source": -1, "src_x": 534, "src_y": 159, "width": 8}, {"dx": 14, "dst_x": 360, "dy": 4, "height": 16, "dst_y": 168, "source": 1, "src_x": 346, "src_y": 164, "width": 16}, {"dx": -9, "dst_x": 376, "dy": -4, "height": 16, "dst_y": 168, "source": -1, "src_x": 385, "src_y": 172, "width": 16}, {"dx": 11, "dst_x": 376, "dy": 7, "height": 16, "dst_y": 168, "source": 1, "src_x": 365, "src_y": 161, "width": 16}, {"dx": -7, "dst_x": 392, "dy": -5, "height": 16, "dst_y": 168, "source": -1, "src_x": 399, "src_y": 173, "width": 16}, {"dx": 11, "dst_x": 392, "dy": 6, "height": 16, "dst_y": 168, "source": 1, "src_x": 381, "src_y": 162, "width": 16}, {"dx": -9, "dst_x": 408, "dy": -5, "height": 16, "dst_y": 168, "source": -1, "src_x": 417, "src_y": 173, "width": 16}, {"dx": 13, "dst_x": 408, "dy": 6, "height": 16, "dst_y": 168, "source": 1, "src_x": 395, "src_y": 162, "width": 16}, {"dx": 12, "dst_x": 424, "dy": 6, "height": 16, "dst_y": 168, "source": 1, "src_x": 412, "src_y": 162, "width": 16}, {"dx": 12, "dst_x": 440, "dy": 6, "height": 16, "dst_y": 168, "source": 1, "src_x": 428, "src_y": 162, "width": 16}, {"dx": -10, "dst_x": 456, "dy": -4, "height": 16, "dst_y": 168, "source": -1, "src_x": 466, "src_y": 172, "width": 16}, {"dx": 12, "dst_x": 456, "dy": 6, "height": 16, "dst_y": 168, "source": 1, "src_x": 444, "src_y": 162, "width": 16}, {"dx": -10, "dst_x": 472, "dy": -4, "height": 16, "dst_y": 168, "source": -1, "src_x": 482, "src_y": 172, "width": 16}, {"dx": 14, "dst_x": 472, "dy": 6, "height": 16, "dst_y": 168, "source": 1, "src_x": 458, "src_y": 162, "width": 16}, {"dx": -10, "dst_x": 484, "dy": -3, "height": 8, "dst_y": 164, "source": -1, "src_x": 494, "src_y": 167, "width": 8}, {"dx": -10, "dst_x": 492, "dy": -3, "height": 8, "dst_y": 164, "source": -1, "src_x": 502, "src_y": 167, "width": 8}, {"dx": -10, "dst_x": 484, "dy": -4, "height": 8, "dst_y": 172, "source": -1, "src_x": 494, "src_y": 176, "width": 8}, {"dx": 14, "dst_x": 484, "dy": 6, "height": 8, "dst_y": 164, "source": 1, "src_x": 470, "src_y": 158, "width": 8}, {"dx": 14, "dst_x": 492, "dy": 6, "height": 8, "dst_y": 164, "source": 1, "src_x": 478, "src_y": 158, "width": 8}, {"dx": 1, "dst_x": 492, "dy": 0, "height": 8, "dst_y": 172, "source": 1, "src_x": 491, "src_y": 172, "width": 8}, {"dx": -10, "dst_x": 524, "dy": -3, "height": 16, "dst_y": 168, "source": -1, "src_x": 534, "src_y": 171, "width": 8}, {"dx": -8, "dst_x": 364, "dy": -4, "height": 16, "dst_y": 184, "source": -1, "src_x": 372, "src_y": 188, "width": 8}, {"dx": 11, "dst_x": 364, "dy": 7, "height": 16, "dst_y": 184, "source": 1, "src_x": 353, "src_y": 177, "width": 8}, {"dx": -8, "dst_x": 376, "dy": -5, "height": 16, "dst_y": 184, "source": -1, "src_x": 384, "src_y": 189, "width": 16}, {"dx": -8, "dst_x": 392, "dy": -4, "height": 16, "dst_y": 184, "source": -1, "src_x": 400, "src_y": 188, "width": 16}, {"dx": 11, "dst_x": 392, "dy": 6, "height": 16, "dst_y": 184, "source": 1, "src_x": 381, "src_y": 178, "width": 16}, {"dx": -8, "dst_x": 408, "dy": -4, "height": 16, "dst_y": 184, "source": -1, "src_x": 416, "src_y": 188, "width": 16}, {"dx": 12, "dst_x": 408, "dy": 6, "height": 16, "dst_y": 184, "source": 1, "src_x": 396, "src_y": 178, "width": 16}, {"dx": -9, "dst_x": 424, "dy": -4, "height": 16, "dst_y": 184, "source": -1, "src_x": 433, "src_y": 188, "width": 16}, {"dx": 13, "dst_x": 424, "dy": 6, "height": 16, "dst_y": 184, "source": 1, "src_x": 411, "src_y": 178, "width": 16}, {"dx": -13, "dst_x": 444, "dy": -4, "height": 16, "dst_y": 184, "source": -1, "src_x": 457, "src_y": 188, "width": 8}, {"dx": 13, "dst_x": 436, "dy": 6, "height": 16, "dst_y": 184, "source": 1, "src_x": 423, "src_y": 178, "width": 8}, {"dx": 12, "dst_x": 444, "dy": 6, "height": 16, "dst_y": 184, "source": 1, "src_x": 432, "src_y": 178, "width": 8}, {"dx": -11, "dst_x": 456, "dy": -5, "height": 16, "dst_y": 184, "source": -1, "src_x": 467, "src_y": 189, "width": 16}, {"dx": 15, "dst_x": 456, "dy": 6, "height": 16, "dst_y": 184, "source": 1, "src_x": 441, "src_y": 178, "width": 16}, {"dx": -10, "dst_x": 472, "dy": -4, "height": 16, "dst_y": 184, "source": -1, "src_x": 482, "src_y": 188, "width": 16}, {"dx": 14, "dst_x": 472, "dy": 6, "height": 16, "dst_y": 184, "source": 1, "src_x": 458, "src_y": 178, "width": 16}, {"dx": -11, "dst_x": 488, "dy": -5, "height": 16, "dst_y": 184, "source": -1, "src_x": 499, "src_y": 189, "width": 16}, {"dx": 15, "dst_x": 488, "dy": 6, "height": 16, "dst_y": 184, "source": 1, "src_x": 473, "src_y": 178, "width": 16}, {"dx": -12, "dst_x": 504, "dy": -5, "height": 8, "dst_y": 180, "source": -1, "src_x": 516, "src_y": 185, "width": 16}, {"dx": -11, "dst_x": 504, "dy": -5, "height": 8, "dst_y": 188, "source": -1, "src_x": 515, "src_y": 193, "width": 16}, {"dx": 16, "dst_x": 504, "dy": 6, "height": 8, "dst_y": 188, "source": 1, "src_x": 488, "src_y": 182, "width": 16}, {"dx": -10, "dst_x": 520, "dy": -3, "height": 16, "dst_y": 184, "source": -1, "src_x": 530, "src_y": 187, "width": 16}, {"dx": -7, "dst_x": 364, "dy": -5, "height": 16, "dst_y": 200, "source": -1, "src_x": 371, "src_y": 205, "width": 8}, {"dx": -8, "dst_x": 372, "dy": -5, "height": 16, "dst_y": 200, "source": -1, "src_x": 380, "src_y": 205, "width": 8}, {"dx": 11, "dst_x": 380, "dy": 7, "height": 16, "dst_y": 200, "source": 1, "src_x": 369, "src_y": 193, "width": 8}, {"dx": -8, "dst_x": 392, "dy": -5, "height": 16, "dst_y": 200, "source": -1, "src_x": 400, "src_y": 205, "width": 16}, {"dx": 11, "dst_x": 392, "dy": 7, "height": 16, "dst_y": 200, "source": 1, "src_x": 381, "src_y": 193, "width": 16}, {"dx": -9, "dst_x": 408, "dy": -5, "height": 16, "dst_y": 200, "source": -1, "src_x": 417, "src_y": 205, "width": 16}, {"dx": 12, "dst_x": 408, "dy": 7, "height": 16, "dst_y": 200, "source": 1, "src_x": 396, "src_y": 193, "width": 16}, {"dx": -9, "dst_x": 424, "dy": -4, "height": 16, "dst_y": 200, "source": -1, "src_x": 433, "src_y": 204, "width": 16}, {"dx": 13, "dst_x": 424, "dy": 7, "height": 16, "dst_y": 200, "source": 1, "src_x": 411, "src_y": 193, "width": 16}, {"dx": -9, "dst_x": 440, "dy": -4, "height": 16, "dst_y": 200, "source": -1, "src_x": 449, "src_y": 204, "width": 16}, {"dx": 13, "dst_x": 440, "dy": 6, "height": 16, "dst_y": 200, "source": 1, "src_x": 427, "src_y": 194, "width": 16}, {"dx": -10, "dst_x": 456, "dy": -4, "height": 16, "dst_y": 200, "source": -1, "src_x": 466, "src_y": 204, "width": 16}, {"dx": 14, "dst_x": 456, "dy": 6, "height": 16, "dst_y": 200, "source": 1, "src_x": 442, "src_y": 194, "width": 16}, {"dx": -11, "dst_x": 472, "dy": -3, "height": 8, "dst_y": 196, "source": -1, "src_x": 483, "src_y": 199, "width": 16}, {"dx": -10, "dst_x": 472, "dy": -4, "height": 8, "dst_y": 204, "source": -1, "src_x": 482, "src_y": 208, "width": 16}, {"dx": 16, "dst_x": 472, "dy": 7, "height": 8, "dst_y": 204, "source": 1, "src_x": 456, "src_y": 197, "width": 16}, {"dx": 15, "dst_x": 488, "dy": 7, "height": 16, "dst_y": 200, "source": 1, "src_x": 473, "src_y": 193, "width": 16}, {"dx": -11, "dst_x": 504, "dy": -5, "height": 16, "dst_y": 200, "source": -1, "src_x": 515, "src_y": 205, "width": 16}, {"dx": 16, "dst_x": 504, "dy": 7, "height": 16, "dst_y": 200, "source": 1, "src_x": 488, "src_y": 193, "width": 16}, {"dx": -10, "dst_x": 520, "dy": -2, "height": 16, "dst_y": 200, "source": -1, "src_x": 530, "src_y": 202, "width": 16}, {"dx": -7, "dst_x": 364, "dy": -5, "height": 16, "dst_y": 216, "source": -1, "src_x": 371, "src_y": 221, "width": 8}, {"dx": -7, "dst_x": 372, "dy": -5, "height": 16, "dst_y": 216, "source": -1, "src_x": 379, "src_y": 221, "width": 8}, {"dx": 11, "dst_x": 380, "dy": 8, "height": 16, "dst_y": 216, "source": 1, "src_x": 369, "src_y": 208, "width": 8}, {"dx": -8, "dst_x": 392, "dy": -5, "height": 16, "dst_y": 216, "source": -1, "src_x": 400, "src_y": 221, "width": 16}, {"dx": 11, "dst_x": 392, "dy": 7, "height": 16, "dst_y": 216, "source": 1, "src_x": 381, "src_y": 209, "width": 16}, {"dx": -9, "dst_x": 408, "dy": -5, "height": 16, "dst_y": 216, "source": -1, "src_x": 417, "src_y": 221, "width": 16}, {"dx": 12, "dst_x": 408, "dy": 7, "height": 16, "dst_y": 216, "source": 1, "src_x": 396, "src_y": 209, "width": 16}, {"dx": -9, "dst_x": 424, "dy": -5, "height": 16, "dst_y": 216, "source": -1, "src_x": 433, "src_y": 221, "width": 16}, {"dx": 13, "dst_x": 424, "dy": 7, "height": 16, "dst_y": 216, "source": 1, "src_x": 411, "src_y": 209, "width": 16}, {"dx": -10, "dst_x": 440, "dy": -6, "height": 8, "dst_y": 220, "source": -1, "src_x": 450, "src_y": 226, "width": 16}, {"dx": 13, "dst_x": 440, "dy": 7, "height": 8, "dst_y": 212, "source": 1, "src_x": 427, "src_y": 205, "width": 16}, {"dx": -10, "dst_x": 456, "dy": -5, "height": 16, "dst_y": 216, "source": -1, "src_x": 466, "src_y": 221, "width": 16}, {"dx": 16, "dst_x": 456, "dy": 7, "height": 16, "dst_y": 216, "source": 1, "src_x": 440, "src_y": 209, "width": 16}, {"dx": -11, "dst_x": 472, "dy": -5, "height": 16, "dst_y": 216, "source": -1, "src_x": 483, "src_y": 221, "width": 16}, {"dx": 15, "dst_x": 472, "dy": 7, "height": 16, "dst_y": 216, "source": 1, "src_x": 457, "src_y": 209, "width": 16}, {"dx": -11, "dst_x": 488, "dy": -5, "height": 8, "dst_y": 212, "source": -1, "src_x": 499, "src_y": 217, "width": 16}, {"dx": -11, "dst_x": 488, "dy": -6, "height": 8, "dst_y": 220, "source": -1, "src_x": 499, "src_y": 226, "width": 16}, {"dx": 15, "dst_x": 488, "dy": 7, "height": 8, "dst_y": 212, "source": 1, "src_x": 473, "src_y": 205, "width": 16}, {"dx": -11, "dst_x": 504, "dy": -5, "height": 16, "dst_y": 216, "source": -1, "src_x": 515, "src_y": 221, "width": 16}, {"dx": 16, "dst_x": 504, "dy": 7, "height": 16, "dst_y": 216, "source": 1, "src_x": 488, "src_y": 209, "width": 16}, {"dx": -10, "dst_x": 516, "dy": -2, "height": 8, "dst_y": 212, "source": -1, "src_x": 526, "src_y": 214, "width": 8}, {"dx": -10, "dst_x": 524, "dy": -2, "height": 8, "dst_y": 212, "source": -1, "src_x": 534, "src_y": 214, "width": 8}, {"dx": -10, "dst_x": 516, "dy": -2, "height": 8, "dst_y": 220, "source": -1, "src_x": 526, "src_y": 222, "width": 8}, {"dx": -10, "dst_x": 524, "dy": -2, "height": 8, "dst_y": 220, "source": -1, "src_x": 534, "src_y": 222, "width": 8}, {"dx": -7, "dst_x": 364, "dy": -6, "height": 16, "dst_y": 232, "source": -1, "src_x": 371, "src_y": 238, "width": 8}, {"dx": -7, "dst_x": 376, "dy": -5, "height": 16, "dst_y": 232, "source": -1, "src_x": 383, "src_y": 237, "width": 16}, {"dx": 10, "dst_x": 376, "dy": 8, "height": 16, "dst_y": 232, "source": 1, "src_x": 366, "src_y": 224, "width": 16}, {"dx": -8, "dst_x": 392, "dy": -5, "height": 16, "dst_y": 232, "source": -1, "src_x": 400, "src_y": 237, "width": 16}, {"dx": 11, "dst_x": 392, "dy": 8, "height": 16, "dst_y": 232, "source": 1, "src_x": 381, "src_y": 224, "width": 16}, {"dx": -9, "dst_x": 408, "dy": -6, "height": 16, "dst_y": 232, "source": -1, "src_x": 417, "src_y": 238, "width": 16}, {"dx": 12, "dst_x": 408, "dy": 8, "height": 16, "dst_y": 232, "source": 1, "src_x": 396, "src_y": 224, "width": 16}, {"dx": -9, "dst_x": 424, "dy": -6, "height": 8, "dst_y": 228, "source": -1, "src_x": 433, "src_y": 234, "width": 16}, {"dx": -9, "dst_x": 424, "dy": -6, "height": 8, "dst_y": 236, "source": -1, "src_x": 433, "src_y": 242, "width": 16}, {"dx": -10, "dst_x": 440, "dy": -6, "height": 16, "dst_y": 232, "source": -1, "src_x": 450, "src_y": 238, "width": 16}, {"dx": 14, "dst_x": 440, "dy": 8, "height": 16, "dst_y": 232, "source": 1, "src_x": 426, "src_y": 224, "width": 16}, {"dx": -10, "dst_x": 456, "dy": -6, "height": 16, "dst_y": 232, "source": -1, "src_x": 466, "src_y": 238, "width": 16}, {"dx": 14, "dst_x": 456, "dy": 8, "height": 16, "dst_y": 232, "source": 1, "src_x": 442, "src_y": 224, "width": 16}, {"dx": -11, "dst_x": 472, "dy": -6, "height": 16, "dst_y": 232, "source": -1, "src_x": 483, "src_y": 238, "width": 16}, {"dx": 15, "dst_x": 472, "dy": 8, "height": 16, "dst_y": 232, "source": 1, "src_x": 457, "src_y": 224, "width": 16}, {"dx": -11, "dst_x": 488, "dy": -6, "height": 16, "dst_y": 232, "source": -1, "src_x": 499, "src_y": 238, "width": 16}, {"dx": 15, "dst_x": 488, "dy": 8, "height": 16, "dst_y": 232, "source": 1, "src_x": 473, "src_y": 224, "width": 16}, {"dx": 16, "dst_x": 504, "dy": 8, "height": 8, "dst_y": 228, "source": 1, "src_x": 488, "src_y": 220, "width": 16}, {"dx": 15, "dst_x": 504, "dy": 8, "height": 8, "dst_y": 236, "source": 1, "src_x": 489, "src_y": 228, "width": 16}, {"dx": -12, "dst_x": 516, "dy": -6, "height": 16, "dst_y": 232, "source": -1, "src_x": 528, "src_y": 238, "width": 8}, {"dx": -10, "dst_x": 524, "dy": -5, "height": 16, "dst_y": 232, "source": -1, "src_x": 534, "src_y": 237, "width": 8}, {"dx": 10, "dst_x": 364, "dy": 8, "height": 16, "dst_y": 248, "source": 1, "src_x": 354, "src_y": 240, "width": 8}, {"dx": -7, "dst_x": 376, "dy": -6, "height": 8, "dst_y": 244, "source": -1, "src_x": 383, "src_y": 250, "width": 16}, {"dx": -7, "dst_x": 376, "dy": -6, "height": 8, "dst_y": 252, "source": -1, "src_x": 383, "src_y": 258, "width": 16}, {"dx": -8, "dst_x": 392, "dy": -6, "height": 16, "dst_y": 248, "source": -1, "src_x": 400, "src_y": 254, "width": 16}, {"dx": 11, "dst_x": 392, "dy": 9, "height": 16, "dst_y": 248, "source": 1, "src_x": 381, "src_y": 239, "width": 16}, {"dx": -9, "dst_x": 408, "dy": -6, "height": 16, "dst_y": 248, "source": -1, "src_x": 417, "src_y": 254, "width": 16}, {"dx": 12, "dst_x": 408, "dy": 8, "height": 16, "dst_y": 248, "source": 1, "src_x": 396, "src_y": 240, "width": 16}, {"dx": -9, "dst_x": 424, "dy": -6, "height": 16, "dst_y": 248, "source": -1, "src_x": 433, "src_y": 254, "width": 16}, {"dx": 12, "dst_x": 424, "dy": 8, "height": 16, "dst_y": 248, "source": 1, "src_x": 412, "src_y": 240, "width": 16}, {"dx": -10, "dst_x": 440, "dy": -6, "height": 16, "dst_y": 248, "source": -1, "src_x": 450, "src_y": 254, "width": 16}, {"dx": 14, "dst_x": 440, "dy": 8, "height": 16, "dst_y": 248, "source": 1, "src_x": 426, "src_y": 240, "width": 16}, {"dx": -10, "dst_x": 456, "dy": -6, "height": 16, "dst_y": 248, "source": -1, "src_x": 466, "src_y": 254, "width": 16}, {"dx": -11, "dst_x": 472, "dy": -6, "height": 16, "dst_y": 248, "source": -1, "src_x": 483, "src_y": 254, "width": 16}, {"dx": 15, "dst_x": 472, "dy": 8, "height": 16, "dst_y": 248, "source": 1, "src_x": 457, "src_y": 240, "width": 16}, {"dx": -11, "dst_x": 488, "dy": -6, "height": 16, "dst_y": 248, "source": -1, "src_x": 499, "src_y": 254, "width": 16}, {"dx": 15, "dst_x": 488, "dy": 9, "height": 16, "dst_y": 248, "source": 1, "src_x": 473, "src_y": 239, "width": 16}, {"dx": -11, "dst_x": 504, "dy": -6, "height": 16, "dst_y": 248, "source": -1, "src_x": 515, "src_y": 254, "width": 16}, {"dx": 15, "dst_x": 504, "dy": 8, "height": 16, "dst_y": 248, "source": 1, "src_x": 489, "src_y": 240, "width": 16}, {"dx": -12, "dst_x": 516, "dy": -6, "height": 16, "dst_y": 248, "source": -1, "src_x": 528, "src_y": 254, "width": 8}, {"dx": -10, "dst_x": 524, "dy": -2, "height": 16, "dst_y": 248, "source": -1, "src_x": 534, "src_y": 250, "width": 8}, {"dx": 0, "dst_x": 360, "dy": 1, "height": 8, "dst_y": 260, "source": -1, "src_x": 360, "src_y": 259, "width": 16}, {"dx": 14, "dst_x": 360, "dy": 9, "height": 8, "dst_y": 268, "source": 1, "src_x": 346, "src_y": 259, "width": 16}, {"dx": -7, "dst_x": 376, "dy": -6, "height": 8, "dst_y": 260, "source": -1, "src_x": 383, "src_y": 266, "width": 16}, {"dx": 8, "dst_x": 376, "dy": 9, "height": 8, "dst_y": 268, "source": 1, "src_x": 368, "src_y": 259, "width": 16}, {"dx": -8, "dst_x": 392, "dy": -9, "height": 8, "dst_y": 260, "source": -1, "src_x": 400, "src_y": 269, "width": 16}, {"dx": 11, "dst_x": 392, "dy": 9, "height": 8, "dst_y": 268, "source": 1, "src_x": 381, "src_y": 259, "width": 16}, {"dx": -9, "dst_x": 408, "dy": -6, "height": 8, "dst_y": 260, "source": -1, "src_x": 417, "src_y": 266, "width": 16}, {"dx": 12, "dst_x": 408, "dy": 9, "height": 8, "dst_y": 268, "source": 1, "src_x": 396, "src_y": 259, "width": 16}, {"dx": -9, "dst_x": 424, "dy": -7, "height": 8, "dst_y": 260, "source": -1, "src_x": 433, "src_y": 267, "width": 16}, {"dx": 12, "dst_x": 424, "dy": 9, "height": 8, "dst_y": 268, "source": 1, "src_x": 412, "src_y": 259, "width": 16}, {"dx": -10, "dst_x": 440, "dy": -7, "height": 8, "dst_y": 260, "source": -1, "src_x": 450, "src_y": 267, "width": 16}, {"dx": 12, "dst_x": 440, "dy": 9, "height": 8, "dst_y": 268, "source": 1, "src_x": 428, "src_y": 259, "width": 16}, {"dx": -10, "dst_x": 456, "dy": -7, "height": 8, "dst_y": 260, "source": -1, "src_x": 466, "src_y": 267, "width": 16}, {"dx": 12, "dst_x": 456, "dy": 9, "height": 8, "dst_y": 268, "source": 1, "src_x": 444, "src_y": 259, "width": 16}, {"dx": -11, "dst_x": 472, "dy": -7, "height": 8, "dst_y": 260, "source": -1, "src_x": 483, "src_y": 267, "width": 16}, {"dx": -41, "dst_x": 472, "dy": -27, "height": 8, "dst_y": 268, "source": -1, "src_x": 513, "src_y": 295, "width": 16}, {"dx": -11, "dst_x": 488, "dy": -7, "height": 8, "dst_y": 260, "source": -1, "src_x": 499, "src_y": 267, "width": 16}, {"dx": -41, "dst_x": 488, "dy": -27, "height": 8, "dst_y": 268, "source": -1, "src_x": 529, "src_y": 295, "width": 16}, {"dx": -41, "dst_x": 504, "dy": -27, "height": 8, "dst_y": 268, "source": -1, "src_x": 545, "src_y": 295, "width": 16}, {"dx": 16, "dst_x": 504, "dy": 9, "height": 8, "dst_y": 260, "source": 1, "src_x": 488, "src_y": 251, "width": 16}, {"dx": -12, "dst_x": 516, "dy": -6, "height": 8, "dst_y": 260, "source": -1, "src_x": 528, "src_y": 266, "width": 8}, {"dx": -10, "dst_x": 524, "dy": -2, "height": 8, "dst_y": 260, "source": -1, "src_x": 534, "src_y": 262, "width": 8}, {"dx": -41, "dst_x": 516, "dy": -27, "height": 8, "dst_y": 268, "source": -1, "src_x": 557, "src_y": 295, "width": 8}, {"dx": -43, "dst_x": 524, "dy": -27, "height": 8, "dst_y": 268, "source": -1, "src_x": 567, "src_y": 295, "width": 8}, {"dx": 8, "dst_x": 376, "dy": 9, "height": 16, "dst_y": 280, "source": 1, "src_x": 368, "src_y": 271, "width": 16}, {"dx": 11, "dst_x": 392, "dy": 10, "height": 16, "dst_y": 280, "source": 1, "src_x": 381, "src_y": 270, "width": 16}, {"dx": 9, "dst_x": 408, "dy": 10, "height": 16, "dst_y": 280, "source": 1, "src_x": 399, "src_y": 270, "width": 16}, {"dx": 7, "dst_x": 424, "dy": 10, "height": 8, "dst_y": 276, "source": 1, "src_x": 417, "src_y": 266, "width": 16}, {"dx": 5, "dst_x": 424, "dy": 10, "height": 8, "dst_y": 284, "source": 1, "src_x": 419, "src_y": 274, "width": 16}, {"dx": 6, "dst_x": 440, "dy": 10, "height": 8, "dst_y": 276, "source": 1, "src_x": 434, "src_y": 266, "width": 16}, {"dx": 5, "dst_x": 440, "dy": 10, "height": 8, "dst_y": 284, "source": 1, "src_x": 435, "src_y": 274, "width": 16}, {"dx": -41, "dst_x": 456, "dy": -27, "height": 8, "dst_y": 276, "source": -1, "src_x": 497, "src_y": 303, "width": 16}, {"dx": 5, "dst_x": 456, "dy": 10, "height": 8, "dst_y": 284, "source": 1, "src_x": 451, "src_y": 274, "width": 16}, {"dx": -41, "dst_x": 472, "dy": -27, "height": 8, "dst_y": 276, "source": -1, "src_x": 513, "src_y": 303, "width": 16}, {"dx": 10, "dst_x": 472, "dy": 11, "height": 8, "dst_y": 284, "source": 1, "src_x": 462, "src_y": 273, "width": 16}, {"dx": -41, "dst_x": 488, "dy": -28, "height": 8, "dst_y": 276, "source": -1, "src_x": 529, "src_y": 304, "width": 16}, {"dx": 13, "dst_x": 488, "dy": 11, "height": 8, "dst_y": 284, "source": 1, "src_x": 475, "src_y": 273, "width": 16}, {"dx": 16, "dst_x": 504, "dy": 10, "height": 16, "dst_y": 280, "source": 1, "src_x": 488, "src_y": 270, "width": 16}]]